{"skeleton":{"hash":"+3WUgeLKK/A","spine":"4.1.23","x":-933.77,"y":-430.84,"width":1787.52,"height":3142.12},"bones":[{"name":"root","x":30,"y":-1086},{"name":"bone","parent":"root","x":-54.97,"y":-232.26},{"name":"bone2","parent":"bone","x":427.64,"y":521.54},{"name":"bone3","parent":"bone2","length":715.77,"rotation":146.73,"x":-35.06,"y":352.97},{"name":"bone5","parent":"bone","x":-49.74,"y":536.14},{"name":"bone4","parent":"bone5","length":664.57,"rotation":145.75,"x":-46.24,"y":212.15},{"name":"bone6","parent":"bone","x":259.26,"y":1100.22},{"name":"bone7a","parent":"bone6","length":123.46,"rotation":75.31,"x":1.06,"y":159.56},{"name":"bone7b","parent":"bone7a","length":123.46,"x":123.46},{"name":"bone7b2","parent":"bone7b","x":130.78,"y":-5.35},{"name":"bone8","parent":"bone7b2","length":103.38,"rotation":4.13,"x":17.42,"y":-55.85},{"name":"bone9","parent":"bone6","length":110.4,"rotation":-79.63,"x":61.64,"y":117.56,"shearY":15.99},{"name":"bone10","parent":"bone9","length":54.75,"rotation":159.01,"x":162.81,"y":-22.06},{"name":"bone11","parent":"bone6","length":87.07,"rotation":-96.65,"x":-71.05,"y":150.43,"shearY":15.99},{"name":"bone12","parent":"bone11","length":27.85,"rotation":-179.77,"x":120.52,"y":-0.88},{"name":"bone7b3","parent":"bone7b2","length":123.99,"rotation":-153.43,"x":4.19,"y":-122.72},{"name":"bone7b4","parent":"bone7b3","length":77.08,"rotation":15.03,"x":137.26,"y":-0.13},{"name":"bone7b5","parent":"bone7b4","length":33.14,"rotation":3.28,"x":87.33,"y":-0.53},{"name":"bone7b6","parent":"bone7b5","length":37.7,"rotation":27.22,"x":37.41,"y":1.13},{"name":"bone7b7","parent":"bone7b","length":90.23,"rotation":111.65,"x":139.32,"y":87.33},{"name":"bone7b8","parent":"bone7b7","length":95.81,"rotation":-12.89,"x":98.64,"y":-4.17},{"name":"bone7b9","parent":"bone7b8","length":48.27,"rotation":-17.6,"x":113.11,"y":-0.3},{"name":"bone7b10","parent":"bone7b9","length":549.44,"rotation":-15.6,"x":-53.5,"y":34.9},{"name":"bone7a2","parent":"bone7a","length":77.83,"rotation":-130.64,"x":10.48,"y":-158.09},{"name":"bone7a3","parent":"bone7a2","length":65.55,"rotation":28.77,"x":77.83},{"name":"bone13","parent":"bone8","x":399.39,"y":95.14},{"name":"bone14","parent":"bone13","length":95.12,"rotation":-55.81,"x":102.95,"y":-346.53},{"name":"bone15","parent":"bone14","length":77.24,"rotation":-20.94,"x":104.79,"y":1.72},{"name":"bone16","parent":"bone15","length":136.87,"rotation":-24.5,"x":101.3,"y":-10.22},{"name":"bone17","parent":"bone16","length":156.3,"rotation":-40.89,"x":136.87},{"name":"bone18","parent":"bone17","length":129.82,"rotation":-26.51,"x":156.3},{"name":"bone19","parent":"bone18","length":146.55,"rotation":-26.89,"x":130.73,"y":-0.01},{"name":"bone20","parent":"bone8","x":190.38,"y":371.9},{"name":"bone21","parent":"bone8","x":272.79,"y":145.67},{"name":"Ball 1","parent":"bone","x":-211.25,"y":824.95},{"name":"bone7","parent":"bone","x":1228.66,"y":2375.38},{"name":"bone22","parent":"bone","x":-1083.2,"y":1441.25},{"name":"bone23","parent":"bone7","x":-635.89,"y":-55.31},{"name":"bone24","parent":"bone7","x":576.87,"y":-77.37},{"name":"bone25","parent":"bone22","x":-383.49,"y":-87.55},{"name":"bone26","parent":"bone22","x":799.35,"y":3.43},{"name":"bone27","parent":"bone","x":725.78,"y":3103.67},{"name":"bone28a","parent":"bone27","length":349.19,"rotation":-109.13,"x":-34.61,"y":-67.76},{"name":"bone28b","parent":"bone27","length":349.19,"rotation":-109.13,"x":-149.04,"y":-397.66},{"name":"bone28","parent":"bone","length":3032.66,"rotation":94.71,"x":-708.7,"y":57.16},{"name":"bone29","parent":"bone28","x":3133.52,"y":260.76},{"name":"bone30","parent":"bone29","x":2.7,"y":6.31},{"name":"bone31","parent":"bone28","x":568.58,"y":-1233.67},{"name":"bone32","parent":"bone30","x":-1283.8,"y":-885.09},{"name":"bone33","parent":"bone","x":-7.51,"y":2543.83},{"name":"bone7b11","parent":"bone7b10","rotation":38.57,"x":746.78,"y":-45.4},{"name":"bone34","parent":"root","x":158.09,"y":-81.76},{"name":"bone35","parent":"bone33","x":-70.18,"y":-3.31},{"name":"bone36","parent":"bone33","x":118.45,"y":-4.79},{"name":"bone37","parent":"root","x":-729.34,"y":923.73},{"name":"bone38","parent":"root","x":-283.23,"y":891.04,"scaleX":0.871,"scaleY":0.871,"shearX":-12.32,"shearY":4.82},{"name":"Ball 2","parent":"bone","x":241.5,"y":961.23}],"slots":[{"name":"Mask","bone":"root","attachment":"Mask"},{"name":"titlescreen_bg","bone":"root","attachment":"titlescreen_bg"},{"name":"titlescreen_bg_cloud1","bone":"root","attachment":"titlescreen_bg_cloud1"},{"name":"titlescreen_bg_cloud2","bone":"root","attachment":"titlescreen_bg_cloud2"},{"name":"titlescreen_sail","bone":"root","attachment":"titlescreen_sail"},{"name":"titlescreen_wood","bone":"root","attachment":"titlescreen_wood"},{"name":"titlescreen_sail_tie","bone":"root","attachment":"titlescreen_sail_tie"},{"name":"titlescreen_pole","bone":"root","attachment":"titlescreen_pole"},{"name":"titlescreen_ropes","bone":"root","attachment":"titlescreen_ropes"},{"name":"titlescreen_cannonB_sideback","bone":"root","attachment":"titlescreen_cannonB_sideback"},{"name":"titlescreen_light_ray","bone":"root","attachment":"titlescreen_light_ray"},{"name":"titlescreen_cannonB_back","bone":"root","attachment":"titlescreen_cannonB_back"},{"name":"cannonball_basic","bone":"Ball 1","attachment":"cannonball_basic"},{"name":"titlescreen_cannonB_front","bone":"root","attachment":"titlescreen_cannonB_front"},{"name":"titlescreen_cannonB_sidefront","bone":"root","attachment":"titlescreen_cannonB_sidefront"},{"name":"titlescreen_cannonA_sideback","bone":"root","attachment":"titlescreen_cannonA_sideback"},{"name":"titlescreen_cannonA_back","bone":"root","attachment":"titlescreen_cannonA_back"},{"name":"cannonball_basic3","bone":"Ball 2","attachment":"cannonball_basic"},{"name":"titlescreen_cannonA_front","bone":"root","attachment":"titlescreen_cannonA_front"},{"name":"titlescreen_cannonA_sidefront","bone":"root","attachment":"titlescreen_cannonA_sidefront"},{"name":"cannonball_basic2","bone":"root"},{"name":"cannonball_gold","bone":"root"},{"name":"croco_sword","bone":"root","attachment":"croco_sword"},{"name":"sword_shine","bone":"root","attachment":"sword_shine"},{"name":"croco_hand","bone":"root","attachment":"croco_hand"},{"name":"croco_head","bone":"root","attachment":"croco_head"},{"name":"croco_eyes_half","bone":"root","attachment":"croco_eyes_half"},{"name":"croco_eyes_closed","bone":"root"},{"name":"croco_body","bone":"root","attachment":"croco_body"},{"name":"titlescreen_railings","bone":"root","attachment":"titlescreen_railings"},{"name":"titlescreen_deck","bone":"root","attachment":"titlescreen_deck"},{"name":"titlescreen_start_shadow","bone":"root","blend":"multiply"},{"name":"titlescreen_start","bone":"root"},{"name":"titlescreen_start_push","bone":"root"},{"name":"titlescreen_logo1","bone":"root","attachment":"titlescreen_logo1"},{"name":"2","bone":"bone37"},{"name":"3","bone":"bone38"}],"transform":[{"name":"Back","bones":["bone14"],"target":"bone20","rotation":-55.81,"x":311.96,"y":-623.29,"mixRotate":-1,"mixX":-1,"mixScaleX":-1,"mixShearY":-1},{"name":"title","order":1,"bones":["bone36"],"target":"bone35","x":188.62,"y":-1.48,"mixRotate":-1,"mixX":-1,"mixScaleX":-1,"mixShearY":-1}],"skins":[{"name":"default","attachments":{"2":{"1":{"type":"mesh","uvs":[1,1,0,1,0,0,1,0],"triangles":[1,2,3,1,3,0],"vertices":[255.92,-230.56,-228.08,-230.56,-228.08,246.44,255.92,246.44],"hull":4},"2":{"type":"mesh","uvs":[1,1,0,1,0,0,1,0],"triangles":[1,2,3,1,3,0],"vertices":[255.92,-230.56,-228.08,-230.56,-228.08,246.44,255.92,246.44],"hull":4},"3":{"type":"mesh","uvs":[1,1,0,1,0,0,1,0],"triangles":[1,2,3,1,3,0],"vertices":[255.92,-230.56,-228.08,-230.56,-228.08,246.44,255.92,246.44],"hull":4},"4":{"type":"mesh","uvs":[1,1,0,1,0,0,1,0],"triangles":[1,2,3,1,3,0],"vertices":[255.92,-230.56,-228.08,-230.56,-228.08,246.44,255.92,246.44],"hull":4},"5":{"type":"mesh","uvs":[1,1,0,1,0,0,1,0],"triangles":[1,2,3,1,3,0],"vertices":[255.92,-230.56,-228.08,-230.56,-228.08,246.44,255.92,246.44],"hull":4},"6":{"type":"mesh","uvs":[1,1,0,1,0,0,1,0],"triangles":[1,2,3,1,3,0],"vertices":[255.92,-230.56,-228.08,-230.56,-228.08,246.44,255.92,246.44],"hull":4},"7":{"type":"mesh","uvs":[1,1,0,1,0,0,1,0],"triangles":[1,2,3,1,3,0],"vertices":[255.92,-230.56,-228.08,-230.56,-228.08,246.44,255.92,246.44],"hull":4},"8":{"type":"mesh","uvs":[1,1,0,1,0,0,1,0],"triangles":[1,2,3,1,3,0],"vertices":[255.92,-230.56,-228.08,-230.56,-228.08,246.44,255.92,246.44],"hull":4},"9":{"type":"mesh","uvs":[1,1,0,1,0,0,1,0],"triangles":[1,2,3,1,3,0],"vertices":[255.92,-230.56,-228.08,-230.56,-228.08,246.44,255.92,246.44],"hull":4},"10":{"type":"mesh","uvs":[1,1,0,1,0,0,1,0],"triangles":[1,2,3,1,3,0],"vertices":[255.92,-230.56,-228.08,-230.56,-228.08,246.44,255.92,246.44],"hull":4},"11":{"type":"mesh","uvs":[1,1,0,1,0,0,1,0],"triangles":[1,2,3,1,3,0],"vertices":[255.92,-230.56,-228.08,-230.56,-228.08,246.44,255.92,246.44],"hull":4},"12":{"type":"mesh","uvs":[1,1,0,1,0,0,1,0],"triangles":[1,2,3,1,3,0],"vertices":[255.92,-230.56,-228.08,-230.56,-228.08,246.44,255.92,246.44],"hull":4},"13":{"type":"mesh","uvs":[1,1,0,1,0,0,1,0],"triangles":[1,2,3,1,3,0],"vertices":[255.92,-230.56,-228.08,-230.56,-228.08,246.44,255.92,246.44],"hull":4},"14":{"type":"mesh","uvs":[1,1,0,1,0,0,1,0],"triangles":[1,2,3,1,3,0],"vertices":[255.92,-230.56,-228.08,-230.56,-228.08,246.44,255.92,246.44],"hull":4},"15":{"type":"mesh","uvs":[1,1,0,1,0,0,1,0],"triangles":[1,2,3,1,3,0],"vertices":[255.92,-230.56,-228.08,-230.56,-228.08,246.44,255.92,246.44],"hull":4}},"3":{"1":{"type":"mesh","uvs":[1,1,0,1,0,0,1,0],"triangles":[1,2,3,1,3,0],"vertices":[255.92,-230.56,-228.08,-230.56,-228.08,246.44,255.92,246.44],"hull":4},"2":{"type":"mesh","uvs":[1,1,0,1,0,0,1,0],"triangles":[1,2,3,1,3,0],"vertices":[255.92,-230.56,-228.08,-230.56,-228.08,246.44,255.92,246.44],"hull":4},"3":{"type":"mesh","uvs":[1,1,0,1,0,0,1,0],"triangles":[1,2,3,1,3,0],"vertices":[255.92,-230.56,-228.08,-230.56,-228.08,246.44,255.92,246.44],"hull":4},"4":{"type":"mesh","uvs":[1,1,0,1,0,0,1,0],"triangles":[1,2,3,1,3,0],"vertices":[255.92,-230.56,-228.08,-230.56,-228.08,246.44,255.92,246.44],"hull":4},"5":{"type":"mesh","uvs":[1,1,0,1,0,0,1,0],"triangles":[1,2,3,1,3,0],"vertices":[255.92,-230.56,-228.08,-230.56,-228.08,246.44,255.92,246.44],"hull":4},"6":{"type":"mesh","uvs":[1,1,0,1,0,0,1,0],"triangles":[1,2,3,1,3,0],"vertices":[255.92,-230.56,-228.08,-230.56,-228.08,246.44,255.92,246.44],"hull":4},"7":{"type":"mesh","uvs":[1,1,0,1,0,0,1,0],"triangles":[1,2,3,1,3,0],"vertices":[255.92,-230.56,-228.08,-230.56,-228.08,246.44,255.92,246.44],"hull":4},"8":{"type":"mesh","uvs":[1,1,0,1,0,0,1,0],"triangles":[1,2,3,1,3,0],"vertices":[255.92,-230.56,-228.08,-230.56,-228.08,246.44,255.92,246.44],"hull":4},"9":{"type":"mesh","uvs":[1,1,0,1,0,0,1,0],"triangles":[1,2,3,1,3,0],"vertices":[255.92,-230.56,-228.08,-230.56,-228.08,246.44,255.92,246.44],"hull":4},"10":{"type":"mesh","uvs":[1,1,0,1,0,0,1,0],"triangles":[1,2,3,1,3,0],"vertices":[255.92,-230.56,-228.08,-230.56,-228.08,246.44,255.92,246.44],"hull":4},"11":{"type":"mesh","uvs":[1,1,0,1,0,0,1,0],"triangles":[1,2,3,1,3,0],"vertices":[255.92,-230.56,-228.08,-230.56,-228.08,246.44,255.92,246.44],"hull":4},"12":{"type":"mesh","uvs":[1,1,0,1,0,0,1,0],"triangles":[1,2,3,1,3,0],"vertices":[255.92,-230.56,-228.08,-230.56,-228.08,246.44,255.92,246.44],"hull":4},"13":{"type":"mesh","uvs":[1,1,0,1,0,0,1,0],"triangles":[1,2,3,1,3,0],"vertices":[255.92,-230.56,-228.08,-230.56,-228.08,246.44,255.92,246.44],"hull":4},"14":{"type":"mesh","uvs":[1,1,0,1,0,0,1,0],"triangles":[1,2,3,1,3,0],"vertices":[255.92,-230.56,-228.08,-230.56,-228.08,246.44,255.92,246.44],"hull":4},"15":{"type":"mesh","uvs":[1,1,0,1,0,0,1,0],"triangles":[1,2,3,1,3,0],"vertices":[255.92,-230.56,-228.08,-230.56,-228.08,246.44,255.92,246.44],"hull":4}},"cannonball_basic":{"cannonball_basic":{"type":"mesh","uvs":[0.55399,0,0.83552,0.07225,1,0.37821,1,0.55175,0.93748,0.80718,0.64911,0.99969,0.28432,0.99389,0.01555,0.71564,0,0.48044,0,0.34835,0.18316,0.08065,0.42717,0,0.43018,0.09114,0.25005,0.1532,0.1108,0.32727,0.11534,0.47107,0.1441,0.63151,0.3439,0.76774,0.56187,0.73596,0.71475,0.59821,0.72383,0.42112,0.69204,0.25915,0.59971,0.13201,0.36509,0.41809],"triangles":[12,11,0,13,10,11,22,0,1,12,0,22,12,13,11,21,22,1,14,10,13,14,9,10,21,1,2,23,13,12,23,12,22,23,22,21,14,13,23,20,21,2,23,21,20,15,14,23,9,14,15,8,9,15,20,2,3,19,23,20,19,20,3,16,15,23,16,7,8,16,8,15,18,23,19,17,16,23,18,17,23,4,19,3,17,7,16,6,7,17,4,5,18,4,18,19,17,18,5,6,17,5],"vertices":[1,34,24.47,157.07,1,1,34,110.05,135.1,1,1,34,160.05,42.09,1,1,34,160.05,-10.66,1,1,34,141.05,-88.32,1,1,34,53.38,-146.84,1,1,34,-57.51,-145.07,1,1,34,-139.22,-60.49,1,1,34,-143.95,11.01,1,1,34,-143.95,51.17,1,1,34,-88.27,132.55,1,1,34,-14.09,157.07,1,1,34,-13.17,129.36,1,1,34,-67.93,110.5,1,1,34,-110.26,57.58,1,1,34,-108.88,13.86,1,1,34,-100.14,-34.91,1,1,34,-39.4,-76.33,1,1,34,26.86,-66.66,1,1,34,73.34,-24.79,1,1,34,76.1,29.05,1,1,34,66.43,78.29,1,1,34,38.36,116.94,1,1,34,-32.96,29.97,1],"hull":12}},"cannonball_basic2":{"cannonball_basic2":{"x":2028,"y":-1168.5,"width":632,"height":621}},"cannonball_basic3":{"cannonball_basic":{"type":"mesh","uvs":[0.55399,0,0.83552,0.07225,1,0.37821,1,0.55175,0.93748,0.80718,0.64911,0.99969,0.28432,0.99389,0.01555,0.71564,0,0.48044,0,0.34835,0.18316,0.08065,0.42717,0,0.43018,0.09114,0.25005,0.1532,0.1108,0.32727,0.11534,0.47107,0.1441,0.63151,0.3439,0.76774,0.56187,0.73596,0.71475,0.59821,0.72383,0.42112,0.69204,0.25915,0.59971,0.13201,0.36509,0.41809],"triangles":[12,11,0,13,10,11,22,0,1,12,0,22,12,13,11,21,22,1,14,10,13,14,9,10,21,1,2,23,13,12,23,12,22,23,22,21,14,13,23,20,21,2,23,21,20,15,14,23,9,14,15,8,9,15,20,2,3,19,23,20,19,20,3,16,15,23,16,7,8,16,8,15,18,23,19,17,16,23,18,17,23,4,19,3,17,7,16,6,7,17,4,5,18,4,18,19,17,18,5,6,17,5],"vertices":[1,56,24.47,157.07,1,1,56,110.05,135.1,1,1,56,160.05,42.09,1,1,56,160.05,-10.66,1,1,56,141.05,-88.32,1,1,56,53.38,-146.84,1,1,56,-57.51,-145.07,1,1,56,-139.22,-60.49,1,1,56,-143.95,11.01,1,1,56,-143.95,51.17,1,1,56,-88.27,132.55,1,1,56,-14.09,157.07,1,1,56,-13.17,129.36,1,1,56,-67.93,110.5,1,1,56,-110.26,57.58,1,1,56,-108.88,13.86,1,1,56,-100.14,-34.91,1,1,56,-39.4,-76.33,1,1,56,26.86,-66.66,1,1,56,73.34,-24.79,1,1,56,76.1,29.05,1,1,56,66.43,78.29,1,1,56,38.36,116.94,1,1,56,-32.96,29.97,1],"hull":12}},"cannonball_gold":{"cannonball_gold":{"x":1608,"y":-1364,"width":304,"height":304}},"croco_body":{"croco_body":{"type":"mesh","uvs":[0.78902,0.12741,0.60774,0.14684,0.54348,0.12928,0.52275,0.09837,0.48474,0.08783,0.45365,0.05341,0.40666,0.06394,0.37004,0.05622,0.18347,0.20515,0.21249,0.23044,0.04251,0.48826,0.01971,0.48193,0,0.52268,0,0.5859,0.028,0.60698,0.07706,0.62735,0.08501,0.68671,0.10378,0.71248,0.14915,0.76401,0.10816,0.77482,0.08188,0.79581,0.08564,0.8254,0.11911,0.84957,0.18544,0.84798,0.27649,0.8712,0.30153,0.86894,0.36816,0.86293,0.39382,0.86834,0.40915,0.89029,0.44325,0.90937,0.40924,0.92122,0.39839,0.95085,0.40862,0.98175,0.47931,0.99183,0.56117,0.97576,0.63806,0.94613,0.99867,1,1,0.79336,0.90877,0.74689,0.85681,0.73668,0.80184,0.73835,0.78873,0.70124,0.77072,0.69054,0.7375,0.70005,0.7251,0.65939,0.73119,0.64012,0.727,0.61234,0.70688,0.57096,0.698,0.52648,0.72373,0.53885,0.73449,0.54099,0.75274,0.58213,0.75625,0.60806,0.77075,0.64825,0.79414,0.6844,0.81496,0.69915,0.85029,0.69534,0.84795,0.67156,0.84044,0.65578,0.85229,0.67122,0.87279,0.68729,0.89581,0.69342,0.92467,0.69175,0.95701,0.67484,0.96797,0.65646,0.95719,0.62525,0.93947,0.59702,0.91353,0.56414,0.88931,0.53564,0.87597,0.48772,0.88858,0.4645,0.89534,0.434,0.88784,0.40521,0.81986,0.31228,0.83028,0.29723,0.83375,0.27234,0.80954,0.21974,0.7951,0.19355,0.792,0.16253,0.61627,0.21376,0.6238,0.31594,0.63831,0.42795,0.65121,0.48751,0.55894,0.33763,0.52359,0.35624,0.46004,0.331,0.39798,0.33353,0.37464,0.31687,0.31804,0.30879,0.27087,0.26689,0.34202,0.40666,0.31435,0.50021,0.29775,0.68097,0.67972,0.71909,0.61559,0.75377,0.60536,0.83145,0.58285,0.91815,0.54592,0.44478,0.56793,0.55415,0.59645,0.68507,0.22727,0.36358,0.19304,0.46798,0.14985,0.57155,0.11725,0.60635],"triangles":[58,67,66,59,58,66,60,59,66,66,65,60,64,63,65,55,54,58,60,65,61,63,62,65,62,61,65,57,55,58,56,55,57,58,52,51,58,53,52,67,58,68,51,68,58,68,51,69,54,53,58,70,72,71,48,73,72,70,69,72,49,48,50,48,72,50,69,50,72,69,51,50,48,98,82,47,98,48,46,99,47,44,46,45,44,99,46,93,99,44,93,44,43,40,93,43,82,81,48,43,42,41,40,43,41,36,38,37,39,38,36,40,39,36,101,10,100,91,102,101,85,97,90,100,88,90,91,101,100,90,91,100,91,90,97,91,97,98,92,91,98,82,97,81,82,98,97,34,96,35,96,29,95,29,28,27,95,29,27,34,29,96,29,32,31,33,29,34,29,31,30,33,32,29,96,95,35,35,40,36,98,47,99,25,24,92,92,27,26,99,94,27,40,35,95,40,95,93,95,27,94,92,99,27,94,99,93,93,95,94,26,25,92,99,92,98,21,20,19,23,18,92,22,19,18,22,18,23,21,19,22,92,24,23,92,102,91,102,10,101,12,14,13,10,12,11,12,10,14,102,103,10,103,14,10,15,14,103,16,15,103,17,16,103,103,92,17,92,103,102,18,17,92,10,9,100,9,8,7,89,9,7,89,7,6,87,88,89,6,87,89,6,5,4,4,87,6,2,85,4,2,4,3,85,87,4,2,83,85,86,87,85,84,85,83,100,9,89,90,88,87,90,87,86,97,84,83,90,86,85,97,85,84,100,89,88,79,83,2,73,48,81,1,0,78,79,1,78,79,78,77,75,73,76,74,73,75,80,79,77,80,77,76,80,76,73,83,79,80,81,80,73,83,80,81,97,83,81,79,2,1],"vertices":[1,15,-17.62,57.44,1,2,15,-27.83,-42.11,0.37943,8,141.03,-77.96,0.62057,2,15,-44.38,-74.68,0.45413,8,141.25,-41.43,0.54587,1,8,154.51,-26.19,1,1,8,154.72,-4.56,1,1,8,168.37,16.67,1,2,8,156.32,40.18,0.99988,13,-300.09,69.91,1.2E-4,2,8,155.26,60.68,0.99912,13,-301.9,49.46,8.8E-4,1,8,51.49,139.36,1,1,8,42.32,120.48,1,1,13,-49.33,-102.11,1,1,13,-51.27,-114.94,1,1,13,-28.16,-123.13,1,1,13,5.75,-119.18,1,1,13,15.27,-102.59,1,1,13,23.08,-74.56,1,1,13,54.41,-66.51,1,1,13,67.03,-54.66,1,2,13,91.78,-26.7,0.20386,14,28.83,25.71,0.79614,2,13,100.19,-48.37,0.00204,14,20.51,47.41,0.99796,1,14,7.63,60.48,1,1,14,-8.01,56.64,1,1,14,-18.93,36.92,1,4,13,134.52,-1.65,4.0E-4,14,-14,0.83,0.99727,11,71.92,-165.57,7.0E-4,12,33.46,166.55,0.00162,5,13,141.18,49.45,0.21107,14,-20.86,-50.25,0.54766,11,93.25,-118.66,0.10191,12,30.34,115.11,0.13701,7,-160,-1.27,0.00235,5,13,138.37,62.96,0.23339,14,-18.11,-63.77,0.43238,11,94.52,-104.92,0.14071,12,34.08,101.82,0.18922,7,-155.34,-14.25,0.0043,5,13,130.91,98.92,0.16547,14,-10.79,-99.76,0.16187,11,97.92,-68.35,0.2431,12,44.01,66.47,0.4238,7,-142.92,-48.81,0.00576,5,13,132.18,113.25,0.09494,14,-12.11,-114.08,0.0832,11,103.32,-55.03,0.20528,12,43.73,52.08,0.61445,7,-142.17,-63.18,0.00214,5,13,142.98,122.98,0.04767,14,-22.95,-123.77,0.04122,11,116.5,-48.88,0.09878,12,33.64,41.63,0.81213,7,-151.5,-74.33,2.0E-4,3,13,151.04,142.77,0.00755,14,-31.09,-143.53,0.00678,12,26.96,21.33,0.98567,3,13,159.56,124.97,6.9E-4,14,-39.54,-125.69,7.8E-4,12,17.23,38.5,0.99853,3,13,176.15,120.91,1.0E-5,14,-56.11,-121.57,7.0E-5,12,0.4,41.4,0.99992,1,12,-14.96,32.81,1,3,11,177.37,-20.86,0.01606,12,-13.16,-6.34,0.98148,24,-57.9,-170.1,0.00246,1,12,3.65,-48.91,1,1,12,27.16,-87.45,1,1,12,35.05,-287.4,1,1,24,149.85,53.59,1,1,24,93.83,53.64,1,1,24,65.85,45.82,1,1,24,39.26,31.51,1,1,24,23.87,46.22,1,1,24,12.44,46.96,1,1,23,59.98,29.23,1,1,23,38.05,36.13,1,1,23,31.39,44.79,1,1,23,17.75,51.43,1,1,23,-6.92,55.06,1,2,23,-29.45,64.71,0.61428,16,34.9,-46.32,0.38572,1,16,47.25,-36.74,1,1,16,50.95,-32,1,1,17,-13.87,-31.85,1,1,17,-0.8,-37.23,1,1,17,21.96,-41.26,1,1,17,45.29,-39.98,1,1,18,2.13,-40.71,1,1,18,17.36,-28.53,1,1,18,9.36,-18.41,1,1,18,1.31,-13.45,1,1,18,11.27,-16.97,1,1,18,25.43,-18.22,1,1,18,37.86,-14.2,1,1,18,50.73,-4.9,1,1,18,60.77,12.35,1,1,18,60.49,23.96,1,1,18,46.43,34.97,1,1,18,30.02,42.57,1,1,17,22.12,49.33,1,1,17,2.13,45.58,1,1,16,60.46,50.28,1,1,16,52.41,62.13,1,1,16,39.41,72.89,1,1,16,23.68,76.26,1,1,15,83.56,53.47,1,1,15,76.78,60.73,1,1,15,64.02,65.37,1,1,15,33.49,58.2,1,1,15,18.02,53.36,1,1,15,1.27,55.14,1,1,15,8.49,-44.96,1,1,15,63.34,-52.27,1,2,15,124.17,-56.93,0.68,23,-91.84,68.02,0.32,2,23,-61.36,55.55,0.35714,16,4.51,-59.7,0.64286,2,15,67.47,-89.53,0.4733,8,34.57,-78.18,0.5267,1,8,19.93,-61.96,1,1,8,24.26,-24.75,1,3,8,14.3,7.86,0.96412,13,-154.94,82.05,0.00338,7,137.76,7.86,0.0325,3,8,19.75,22.54,0.94917,13,-162.39,68.28,0.00718,7,143.22,22.54,0.04365,1,8,16.09,53.7,1,1,8,31.41,84.49,1,1,7,91.77,27.56,1,1,7,39.06,29.44,1,1,11,-5.69,-88.69,1,2,11,52.3,113.88,0.00923,23,50.39,-2.71,0.99077,1,11,64.39,75.88,1,1,11,104.64,62.8,1,1,12,36.42,-54.87,1,1,7,100.25,-85.94,1,1,7,46.19,-112.61,1,1,11,26,72.22,1,1,7,98.29,94.4,1,1,7,38.99,98.28,1,1,13,-11.48,-38.36,1,1,13,9.26,-53.96,1],"hull":79}},"croco_eyes_closed":{"croco_eyes_closed":{"type":"mesh","uvs":[0.15742,0,0.31476,0.45451,0.51007,0.61122,0.77138,0.35634,1,0.65607,1,0.86073,0.98457,1,0.78555,1,0,0.34698,0,0.1833,0.07168,0],"triangles":[0,8,9,7,3,4,5,7,4,2,3,7,1,2,7,0,9,10,1,8,0,8,1,7,6,7,5],"vertices":[2,33,48.12,65.12,0.92857,32,130.53,-161.11,0.07143,2,33,-11.92,5.27,0.61143,32,70.48,-220.96,0.38857,2,33,-24.76,-57.52,0.6,32,57.64,-283.75,0.4,2,33,28.38,-128.42,0.85714,32,110.79,-354.65,0.14286,2,33,-4.26,-205.21,0.88,32,78.15,-431.43,0.12,2,33,-35.24,-210.98,0.89143,32,47.17,-437.21,0.10857,2,33,-57.18,-210.3,0.94857,32,25.22,-436.53,0.05143,2,33,-68.27,-150.83,0.82571,32,14.13,-377.05,0.17429,2,33,-13.18,102.37,0.87143,32,69.22,-123.86,0.12857,1,33,11.6,106.99,1,2,33,43.34,90.74,0.93714,32,125.75,-135.49,0.06286],"hull":11}},"croco_eyes_half":{"croco_eyes_half":{"type":"mesh","uvs":[0.15886,0,0.23591,0.47532,0.52107,0.69836,0.80613,0.39657,1,0.85185,1,0.99953,0.24355,0.5638,0,0.15513,0,0.07724,0.08335,0],"triangles":[7,8,9,2,6,1,9,0,1,1,7,9,6,7,1,3,4,5,2,3,5,6,2,5],"vertices":[1,33,49.13,59.73,1,1,33,-6.48,26,1,1,33,-18.97,-62.77,1,1,33,34.58,-139.2,1,1,33,-12.12,-206.67,1,1,33,-30.7,-210.14,1,1,33,-17.19,21.69,1,1,33,20.93,102.62,1,1,33,30.73,104.45,1,1,33,45,81.85,1],"hull":10}},"croco_hand":{"croco_hand":{"type":"mesh","uvs":[1,0.51032,1,0.64009,0.78987,1,0.56413,1,0.12345,0.89755,0,0.63158,0,0.52479,0.09738,0,0.15241,0,0.8643,0.15243],"triangles":[4,5,8,3,4,8,7,8,6,8,5,6,1,2,9,2,3,9,9,3,8,9,0,1],"vertices":[1,19,-39.6,11.2,1,1,19,-37.56,27.95,1,1,19,37.36,65.94,1,2,19,111.75,56.85,0.62012,20,-0.83,62.42,0.37988,2,20,146.07,64.28,0.08507,21,11.89,71.52,0.91493,1,21,63.27,56.17,1,1,21,68.81,43.44,1,2,20,166.73,-50.89,0.01136,21,66.4,-32.02,0.98864,2,20,148.56,-52.77,0.05321,21,49.65,-39.31,0.94679,2,19,-0.52,-40.44,0.99364,20,-88.57,-57.47,0.00636],"hull":10}},"croco_head":{"croco_head":{"type":"mesh","uvs":[0.45824,0.04953,0.55417,0.2232,0.56901,0.32244,0.62817,0.27365,0.69761,0.21638,0.8459,0.23144,0.96331,0.39236,1,0.63413,1,0.71196,0.98454,0.77654,0.96824,0.84467,0.88784,0.93475,0.84839,0.90546,0.78049,0.85505,0.78195,0.7626,0.78373,0.64955,0.78805,0.54547,0.7582,0.42354,0.67256,0.34353,0.63097,0.35572,0.59172,0.38857,0.62009,0.47115,0.75288,0.6327,0.76707,0.65334,0.54795,0.85604,0.32921,1,0.3025,1,0.14268,0.86207,0.00634,0.7444,0,0.61158,0,0.52144,0.06444,0.45462,0.13845,0.5131,0.16985,0.49841,0.16031,0.47108,0.15313,0.4505,0.10783,0.32065,0.148,0.23054,0.24486,0.01327,0.34758,9.0E-5,0.16536,0.55046,0.17762,0.56698,0.19951,0.59466,0.20999,0.64951,0.21919,0.72956,0.20523,0.77897,0.18139,0.40493,0.23394,0.36572,0.3757,0.40578,0.44631,0.53108,0.47751,0.68452,0.4693,0.84391,0.41456,0.91978,0.34396,0.93341,0.22737,0.89761,0.17171,0.828,0.31212,0.45781,0.28576,0.54687,0.2972,0.62664,0.34345,0.72965,0.3907,0.77999,0.45137,0.79083,0.47269,0.77803,0.26637,0.42915,0.25145,0.52983,0.21863,0.54842,0.18232,0.543,0.32804,0.54687,0.39915,0.57475,0.44291,0.64755,0.47526,0.72807,0.21614,0.47485,0.18232,0.45703,0.33189,0.3934,0.25677,0.37217,0.57987,0.35407,0.68704,0.2719,0.81182,0.31,0.88425,0.46089,0.91067,0.6293,0.89942,0.79695,0.63125,0.31468,0.99141,0.63616,0.03731,0.55598,0.05417,0.60512,0.10795,0.64533,0.15313,0.64365,0.05775,0.5275,0.10688,0.54593,0.15098,0.59563,0.29727,0.7894],"triangles":[90,44,58,27,28,85,28,84,85,55,85,86,55,27,85,55,86,45,45,44,90,44,86,43,44,45,86,28,29,84,44,43,58,86,42,43,84,88,85,85,89,86,85,88,89,42,89,41,42,86,89,29,83,84,29,30,83,84,87,88,84,83,87,88,32,89,89,40,41,89,32,40,83,30,87,32,88,31,88,87,31,87,30,31,43,42,65,41,66,42,11,80,10,11,12,80,80,12,14,12,13,14,10,80,9,14,15,80,80,79,9,80,15,79,8,79,82,8,9,79,82,7,8,15,16,79,6,7,82,78,82,79,6,82,78,16,78,79,16,17,78,6,78,5,17,77,78,17,76,77,78,77,5,77,4,5,18,76,17,76,4,77,76,3,4,24,22,23,24,21,22,49,20,21,49,75,20,49,2,75,2,49,1,1,48,0,73,39,0,20,75,19,74,38,39,46,36,37,47,37,38,19,81,18,19,75,81,75,2,81,18,81,76,2,3,81,81,3,76,25,52,24,52,51,24,25,53,52,25,26,53,26,27,54,27,55,54,26,54,53,54,90,53,53,90,60,53,60,52,60,90,59,52,61,51,52,60,61,55,45,54,54,45,90,51,62,24,24,62,21,51,61,62,62,61,70,59,90,58,70,61,60,62,70,21,70,50,21,69,70,60,69,60,59,59,58,68,59,68,69,68,58,67,57,58,64,64,58,65,43,65,58,70,69,50,69,49,50,50,49,21,69,68,49,58,57,67,42,66,65,49,68,48,41,40,66,40,33,66,40,32,33,64,65,71,57,56,67,68,67,48,67,56,48,57,64,56,66,33,71,65,66,71,71,33,72,64,63,56,64,71,63,33,34,72,63,71,47,34,35,72,56,73,48,56,63,73,35,46,72,47,71,46,71,72,46,35,36,46,47,74,63,63,74,73,1,49,48,47,46,37,48,73,0,73,74,39,47,38,74],"vertices":[2,10,707.6,-38.88,0.3282,26,-60.44,289.2,0.6718,2,10,590.06,-185.41,0.3282,26,-5.29,109.64,0.6718,2,10,513.53,-218.95,0.3282,26,-20.55,27.48,0.6718,2,26,64.71,33.86,0.88332,27,-48.92,15.7,0.11668,2,27,41.86,58.44,0.99707,28,-82.55,37.83,0.00293,2,28,97.86,96.7,0.98434,29,-92.79,47.56,0.01566,2,29,93.24,120.24,0.9707,30,-110.1,79.45,0.0293,3,29,290.89,70.92,0.00552,30,88.78,123.53,0.87031,31,-93.29,91.22,0.12416,2,30,152.6,122.64,0.56957,31,-35.97,119.29,0.43043,2,30,205.27,102.17,0.23838,31,20.27,124.85,0.76162,2,30,260.84,80.57,0.0452,31,79.6,130.72,0.9548,1,31,191.1,70.99,1,1,31,191.68,15.18,1,3,29,323.25,-261.26,5.0E-5,30,266,-159.28,0.00228,31,192.68,-80.87,0.99766,3,29,256.74,-224.82,0.01453,30,190.23,-156.36,0.07118,31,123.78,-112.53,0.9143,4,28,151.48,-251.11,0.01532,29,175.42,-180.27,0.14594,30,97.56,-152.79,0.34524,31,39.52,-151.26,0.49349,4,28,124.9,-169.83,0.14208,29,102.12,-136.22,0.46703,30,12.31,-146.09,0.28007,31,-39.55,-183.84,0.11081,6,26,167.56,-145.31,0.00858,27,111.17,-114.88,0.03794,28,52.38,-91.15,0.73556,29,-4.21,-124.22,0.19614,30,-88.2,-182.8,0.01917,31,-112.58,-262.04,0.00261,3,26,93.68,-41.36,0.60917,27,5.02,-44.2,0.3336,28,-73.53,-70.85,0.05722,3,10,501.21,-301.74,7.4E-4,26,41.01,-29.23,0.99872,28,-119.13,-99.86,5.4E-4,2,10,465.54,-257.41,0.3282,26,-15.7,-33.83,0.6718,2,10,405.62,-305.43,0.3282,26,-9.66,-110.38,0.6718,2,10,306.46,-496.41,0.31337,26,92.59,-299.71,0.68663,2,10,293.15,-517.32,0.16578,26,102.41,-322.48,0.83422,2,10,78.46,-272.72,0.7859,26,-220.56,-362.61,0.2141,1,10,-88.78,-19.75,1,1,10,-95.03,13.78,1,2,10,-21.25,235.15,0.78989,32,-211.63,-136.75,0.21011,2,10,41.69,423.99,0.38683,32,-148.69,52.09,0.61317,2,10,147.28,451.91,0.2366,32,-43.1,80.01,0.7634,2,10,219.94,465.45,0.2366,32,29.56,93.56,0.7634,2,10,288.89,394.6,0.17484,32,98.51,22.7,0.82516,2,10,259.07,292.9,0.67412,32,68.69,-79,0.32588,3,10,278.26,255.69,0.68466,26,-545.38,99.59,0.16391,32,87.87,-116.2,0.15143,2,10,298.06,271.77,0.73112,26,-547.55,125.01,0.26888,2,10,312.97,283.88,0.7447,26,-549.18,144.15,0.2553,2,10,407.04,360.27,0.3282,26,-559.51,264.89,0.6718,2,10,489.08,323.38,0.3282,26,-482.89,312.01,0.6718,2,10,686.89,234.43,0.3282,26,-298.16,425.66,0.6718,2,10,721.56,107.46,0.32497,26,-173.65,382.98,0.67503,2,10,235.25,253.5,0.64885,32,44.87,-118.4,0.35115,2,10,224.8,235.63,0.34112,32,34.42,-136.27,0.65888,2,10,207.62,203.98,0.23019,32,17.24,-167.91,0.76981,1,32,-24.53,-189.3,1,2,10,103.48,159.01,0.1953,32,-86.91,-212.89,0.8047,2,10,60.37,169.11,0.34965,32,-130.01,-202.79,0.65035,2,10,356.32,255.25,0.69024,26,-501.14,163.91,0.30976,2,10,400.22,195.18,0.80767,26,-426.78,166.47,0.19233,2,10,401.11,11.19,0.6718,26,-274.09,63.82,0.3282,2,10,316.63,-96.28,0.6114,26,-232.67,-66.46,0.3886,2,10,200.25,-158.5,0.6718,26,-246.6,-197.69,0.3282,2,10,69.83,-172.15,0.85207,26,-308.59,-313.24,0.14793,1,10,-4.13,-114.84,1,1,10,-31.65,-28.25,1,1,10,-30.08,123.48,1,2,10,13.01,203.82,0.51131,32,-177.37,-168.08,0.48869,2,10,344.29,83.19,0.8462,26,-365.58,57.28,0.1538,1,10,266.32,102.89,1,2,10,204.7,76.54,0.6718,32,14.32,-295.35,0.3282,2,10,132.49,3,0.6718,32,-57.89,-368.9,0.3282,2,10,102.97,-63.87,0.74262,32,-87.41,-435.77,0.25738,1,10,108.43,-141.67,1,2,10,123.74,-166.51,0.83534,26,-282.97,-265.48,0.16466,2,10,356.68,144.93,0.73391,26,-409.69,102.22,0.26609,2,10,272.03,148.53,0.82,32,81.65,-223.37,0.18,2,10,249.36,186.94,0.87429,32,58.98,-184.96,0.12571,2,10,245.24,233.33,0.78779,32,54.85,-138.57,0.21221,1,10,276.22,49.83,1,1,10,270.39,-43.64,1,2,10,221.95,-109.52,0.84397,26,-274.92,-152.22,0.15603,2,10,164.61,-162.23,0.74857,26,-263.54,-229.26,0.25143,3,10,308.09,201.12,0.67362,26,-483.47,93.6,0.20638,32,117.71,-170.78,0.12,3,10,314.53,246.25,0.57967,26,-517.18,124.29,0.28319,32,124.15,-125.65,0.13714,2,10,400.83,68.05,0.6718,26,-321.28,95.54,0.3282,2,10,400.36,165.55,0.6718,26,-402.19,149.94,0.3282,2,10,490.58,-237.34,0.3282,26,-18.23,-1.83,0.6718,1,27,26.25,13.6,1,1,28,81.38,20.73,1,1,29,96.85,4.76,1,1,30,83.23,9.53,1,1,31,83.11,34.57,1,2,26,54.82,1.46,0.99883,27,-46.57,-18.09,0.00117,3,29,287.34,60.41,0.00594,30,90.29,112.54,0.86787,31,-86.97,82.1,0.1262,1,32,10.45,41.52,1,1,32,-25.22,12.98,1,1,32,-45.04,-60.58,1,1,32,-33.12,-117.05,1,1,32,38.19,20.14,1,1,32,34.83,-44.29,1,1,32,5.09,-107.13,1,2,10,73.51,52,0.55749,32,-116.87,-319.9,0.44251],"hull":40}},"croco_sword":{"croco_sword":{"type":"mesh","uvs":[0.06462,0,0.06721,0,0.07,0.03285,0.07445,0.0511,0.10196,0.10789,0.13002,0.14334,0.15616,0.1691,0.18566,0.18933,0.22571,0.20408,0.37234,0.23176,0.38261,0.25472,0.40411,0.2929,0.46187,0.37544,0.47619,0.39335,0.5275,0.45006,0.55299,0.475,0.64363,0.55305,0.67976,0.57836,0.67553,0.52088,0.71389,0.48652,0.76829,0.48662,0.7982,0.52294,0.78747,0.57424,0.70292,0.66681,0.72258,0.67579,0.81847,0.74288,0.89446,0.79054,0.99518,0.85888,0.99826,0.89076,0.99134,0.90082,0.96782,0.93501,0.91019,0.94841,0.92269,0.94134,0.8138,0.9989,0.76915,0.99833,0.70961,0.96718,0.66297,0.92514,0.61446,0.83116,0.61542,0.76236,0.59175,0.7385,0.37793,0.61243,0.17679,0.47744,0.09232,0.39483,0.0443,0.32358,0.02197,0.28143,9.0E-5,0.20414,0.00584,0.09881,0.03058,0.03255,0.05389,0.00729,0.05948,0.04129,0.05748,0.06065,0.06779,0.13306,0.10054,0.20659,0.15583,0.29097,0.23895,0.37943,0.37754,0.49722,0.49801,0.57849,0.65146,0.66973,0.81698,0.78614,0.93747,0.86799],"triangles":[1,2,49,47,48,49,48,0,1,48,1,49,49,2,3,50,47,49,50,49,3,46,47,50,50,3,4,51,50,4,46,50,51,51,4,5,45,46,51,52,51,5,52,5,6,45,51,52,44,45,52,7,53,52,7,52,6,53,7,8,44,52,53,43,44,53,10,54,8,10,8,9,54,10,11,53,8,54,42,43,53,42,53,54,41,42,54,12,55,54,12,54,11,55,12,13,55,13,14,41,54,55,22,20,21,20,17,18,56,55,14,56,14,15,56,15,16,40,55,56,41,55,40,17,22,23,19,20,18,22,17,20,57,16,17,57,17,23,56,16,57,39,56,57,40,56,39,38,39,57,58,24,25,57,23,24,58,57,24,58,25,26,59,26,27,58,26,59,59,27,28,29,59,28,58,38,57,58,37,38,36,37,58,30,59,29,33,58,32,32,59,30,58,35,36,32,58,59,31,32,30,35,33,34,35,58,33],"vertices":[1,22,767.16,-132.96,1,1,22,765.94,-133.95,1,1,22,750.53,-117.69,1,1,22,740.6,-109.77,1,1,22,703.25,-90.37,1,1,22,674.81,-82.43,1,1,22,651.43,-78.87,1,1,22,628.83,-79.51,1,1,22,603.61,-87.1,1,1,22,522.57,-128.75,1,1,22,507.88,-120.57,1,1,22,481.35,-108.68,1,1,22,418.69,-87.29,1,1,22,404.25,-83.34,1,1,22,355.72,-73.11,1,1,22,332.99,-69.73,1,1,22,256.76,-63.33,1,1,22,228.85,-63.84,1,1,22,255.51,-92.54,1,1,22,252.16,-125.38,1,1,22,226.46,-146.2,1,1,22,196.76,-138.51,1,1,22,179.82,-107.33,1,1,22,179.98,-26.06,1,1,22,166.85,-28.86,1,1,22,92.83,-30.26,1,1,22,36.54,-34.27,1,1,22,-40.29,-36.86,1,1,22,-55.42,-21.23,1,1,22,-56.47,-13.26,1,1,22,-60.05,13.8,1,1,22,-38.61,42.98,1,1,22,-41.48,34.45,1,1,22,-14.81,106.59,1,1,22,6.49,123.42,1,1,22,47.94,129.83,1,1,22,87.98,125.54,1,1,22,151.18,94.58,1,1,22,180.25,57.91,1,1,22,201.65,54.41,1,1,22,356.6,69.93,1,1,22,509.4,75.88,1,1,22,584.69,64.71,1,1,22,637.91,45.54,1,1,22,666.52,31.87,1,1,22,710.01,-0.51,1,1,22,752.49,-58.28,1,1,22,769.25,-102.73,1,1,22,769.09,-125,1,1,22,751.87,-109.21,1,1,22,744.51,-98.22,1,1,22,708.57,-63.98,1,1,22,661.57,-37.75,1,1,22,599.29,-14.45,1,1,22,522.13,0.33,1,1,22,406.21,9.3,1,1,22,314.52,5.96,1,1,22,203,-4.78,1,1,22,74.97,-6.87,1,1,22,-16.98,-9.92,1],"hull":49}},"Mask":{"Mask":{"type":"clipping","end":"Mask","vertexCount":4,"vertices":[831.46,-426.45,-920.86,-431.68,-933.77,2711.28,853.75,2694.39]}},"sword_shine":{"sword_shine":{"type":"mesh","uvs":[0.93864,0.6054,0.55635,0.95575,0.0754,0.70586,0.21355,0.1334,0.72966,0.09168],"triangles":[3,0,2,0,3,4,1,2,0],"vertices":[1,50,-48.5,10.66,1,1,50,-6.9,57.31,1,1,50,46.32,24.83,1,1,50,31.86,-50.88,1,1,50,-24.86,-56.93,1],"hull":5}},"titlescreen_bg":{"titlescreen_bg":{"type":"mesh","uvs":[1,1,0,1,0,0,0.94374,0,1,2.8E-4],"triangles":[1,2,3,3,4,0,1,3,0],"vertices":[933.46,-362.17,-1078.44,-362.17,-1078.44,2808.03,820.26,2808.03,933.46,2807.14],"hull":5}},"titlescreen_bg_cloud1":{"titlescreen_bg_cloud1":{"type":"mesh","uvs":[0,0.76257,0.17346,1,0.58842,1,0.86185,1,1,0.78684,1,0.34035,0.78626,0,0.27639,0,0.07213,0.07585,0,0.31608,0.33439,0.2372,0.24688,0.50024,0.25832,0.76126,0.5599,0.23822,0.51547,0.54696,0.53298,0.76126,0.82244,0.33368,0.76859,0.56016,0.78205,0.77547],"triangles":[5,16,6,16,17,13,4,18,17,15,17,18,17,16,5,5,4,17,3,18,4,2,18,3,13,10,7,2,15,18,12,15,2,6,13,7,14,10,13,17,14,13,15,14,17,12,14,15,13,6,16,10,11,8,10,8,7,9,8,11,11,10,14,12,11,14,0,9,11,0,11,12,1,0,12,1,12,2],"vertices":[1,39,-639.14,-335.9,1,1,39,-262.57,-677.56,1,1,36,254.84,-765.11,1,1,40,49.1,-768.54,1,2,36,1148.37,-458.37,0.02863,40,349.02,-461.81,0.97137,2,36,1148.37,184.13,0.0052,40,349.02,180.69,0.9948,2,36,684.34,673.89,0.42524,40,-115.01,670.46,0.57476,2,39,-39.09,761.44,0.20778,36,-422.58,673.89,0.79222,1,39,-482.56,652.29,1,1,39,-639.14,306.6,1,1,39,86.82,420.11,1,1,39,-103.17,41.59,1,1,39,-78.33,-334,1,1,36,192.92,331.1,1,1,36,96.46,-113.19,1,1,36,134.46,-421.56,1,2,36,762.89,193.72,0.13233,40,-36.46,190.29,0.86767,1,40,-153.38,-135.62,1,1,40,-124.15,-445.45,1],"hull":10}},"titlescreen_bg_cloud2":{"titlescreen_bg_cloud2":{"type":"mesh","uvs":[0.01577,0.63289,0.14155,0.7198,0.48262,0.76905,0.76931,0.76036,1,0.60102,1,0.29828,0.87469,0.1737,0.59707,0,0.33871,0,0.19594,0.04478,0,0.40257,0,0.54598,0.80923,0.27224,0.77116,0.41825,0.77265,0.60339,0.55989,0.15105,0.52107,0.38676,0.50764,0.59862,0.3113,0.10238,0.24187,0.34382,0.24411,0.60244],"triangles":[6,12,7,12,13,15,12,6,5,5,13,12,4,13,5,14,13,4,17,13,14,3,17,14,3,14,4,2,20,17,2,17,3,15,8,7,12,15,7,16,18,15,13,16,15,17,16,13,17,20,16,18,9,8,19,9,18,19,18,16,10,9,19,11,10,19,16,20,19,11,19,20,0,11,20,1,0,20,1,20,2,18,8,15],"vertices":[1,37,-801.86,-522.3,1,1,37,-452.95,-710.9,1,1,35,-142.69,-873.09,1,1,38,75.7,-776.86,1,2,35,1292.51,-508.46,1.0E-5,38,715.65,-431.09,0.99999,2,35,1292.51,148.5,1.4E-4,38,715.65,225.87,0.99986,1,38,368.03,496.2,1,1,35,174.78,795.76,1,1,37,93.99,851.07,1,1,37,-302.07,753.89,1,1,37,-845.6,-22.51,1,1,37,-845.6,-333.7,1,1,38,186.45,282.36,1,1,38,80.84,-34.48,1,1,38,84.98,-436.22,1,1,35,71.65,467.99,1,1,35,-36.03,-43.51,1,1,35,-73.31,-503.24,1,1,37,17.95,628.92,1,1,37,-174.64,104.99,1,1,37,-168.43,-456.21,1],"hull":12}},"titlescreen_cannonA_back":{"titlescreen_cannonA_back":{"type":"mesh","uvs":[0.47262,0,1,0.44819,1,0.51312,0.90596,0.8211,0.64235,1,0.52767,1,0,0.67982,0,0.53037,0.02378,0.27838,0.30605,0],"triangles":[0,1,2,5,6,7,2,5,0,3,5,2,8,9,0,0,7,8,0,5,7,4,5,3],"vertices":[1,3,798.05,-137.28,1,1,3,531.49,-116.54,1,1,3,518.48,-96.73,1,1,3,488.33,17.95,1,1,3,540.88,130.53,1,1,3,579.33,155.76,1,1,3,820.36,174.15,1,1,3,850.28,128.55,1,1,3,892.77,46.42,1,1,3,853.89,-100.63,1],"hull":10}},"titlescreen_cannonA_front":{"titlescreen_cannonA_front":{"type":"mesh","uvs":[0.31132,0.11588,0.3791,0.15808,0.76603,0.33826,0.98794,0.58495,1,0.70294,1,0.79862,0.91709,0.97233,0.79814,1,0.70621,1,0.43489,0.82175,0.14986,0.44466,0.09558,0.42294,0.02617,0.39775,0,0.30838,0,0.28275,0.07033,0.36368,0.14325,0.33256,0.2296,0.19884,0.24331,0.08515,0.18182,0.01188,0.13884,0.01865,0.15616,0,0.16714,0,0.24356,0.0031],"triangles":[19,22,23,20,21,22,20,22,19,18,19,23,18,23,0,17,18,0,14,15,13,12,13,15,11,15,16,12,15,11,10,16,17,11,16,10,3,8,2,9,1,2,17,0,1,1,10,17,9,10,1,9,2,8,5,6,4,8,3,4,4,7,8,6,7,4],"vertices":[1,3,675.22,-119.34,1,1,3,607.36,-127.98,1,1,3,243.66,-213.43,1,1,3,-20.84,-177.22,1,1,3,-76.01,-113.08,1,1,3,-113.34,-56.21,1,1,3,-118.23,88.31,1,1,3,-38.83,163.95,1,1,3,30.89,209.7,1,1,3,306.16,238.76,1,1,3,669.4,156.45,1,1,3,719.04,170.54,1,1,3,781.49,190.11,1,1,3,836.2,150.01,1,1,3,846.2,134.78,1,1,3,761.29,147.89,1,1,3,718.14,93.1,1,1,3,704.82,-29.36,1,1,3,738.78,-103.76,1,1,3,813.99,-116.72,1,1,3,843.94,-91.3,1,1,3,838.08,-111.01,1,1,3,829.75,-116.47,1,1,3,770.59,-152.66,1],"hull":24}},"titlescreen_cannonA_sideback":{"titlescreen_cannonA_sideback":{"type":"mesh","uvs":[0.72699,0,0.9928,0.31653,1,0.7457,1,1,0.82784,1,0.69097,0.98663,0,0.91535,0,0.69606,0.05335,0.28793,0.22961,0.0673,0.51578,0],"triangles":[5,6,7,10,0,1,8,9,10,1,8,10,7,1,2,1,7,8,2,5,7,4,5,2,4,2,3],"vertices":[1,2,-39.23,487.6,1,1,2,79.32,308.13,1,1,2,82.53,64.79,1,1,2,82.53,-79.4,1,1,2,5.75,-79.4,1,1,2,-55.3,-71.82,1,1,2,-363.47,-31.4,1,1,2,-363.47,92.94,1,1,2,-339.68,324.34,1,1,2,-261.07,449.45,1,1,2,-133.43,487.6,1],"hull":11}},"titlescreen_cannonA_sidefront":{"titlescreen_cannonA_sidefront":{"type":"mesh","uvs":[0.9853,0.31573,1,0.68395,1,0.96479,0.84326,1,0.81975,1,0,0.91492,0,0.70216,0.06073,0.22809,0.33196,0,0.52303,0,0.739,0.00704],"triangles":[1,5,6,7,8,9,9,0,7,0,9,10,0,6,7,1,6,0,1,3,4,4,5,1,2,3,1],"vertices":[1,2,315.97,375.58,1,1,2,322.53,166.8,1,1,2,322.53,7.57,1,1,2,252.62,-12.4,1,1,2,242.14,-12.4,1,1,2,-123.47,35.84,1,1,2,-123.47,156.48,1,1,2,-96.38,425.27,1,1,2,24.58,554.6,1,1,2,109.8,554.6,1,1,2,206.12,550.61,1],"hull":11}},"titlescreen_cannonB_back":{"titlescreen_cannonB_back":{"type":"mesh","uvs":[0.4713,0,1,0.44859,1,0.51896,0.9178,0.77791,0.73321,0.95512,0.55684,1,0.53045,1,0.01018,0.6857,0,0.54094,0,0.39556,0.17962,0.08375,0.38675,0],"triangles":[0,1,2,8,9,10,0,7,8,3,0,2,3,6,0,3,5,6,8,10,11,8,11,0,6,7,0,4,5,3],"vertices":[1,5,764.37,-158.09,1,1,5,496.98,-142.06,1,1,5,482.52,-120.83,1,1,5,456.58,-24.15,1,1,5,481.36,70.98,1,1,5,530.6,124.32,1,1,5,539.35,130.27,1,1,5,776.36,152.86,1,1,5,809.48,111.48,1,1,5,839.34,67.62,1,1,5,843.85,-66.99,1,1,5,792.4,-139.01,1],"hull":12}},"titlescreen_cannonB_front":{"titlescreen_cannonB_front":{"type":"mesh","uvs":[0.23182,0,0.35198,0.14142,0.6367,0.27793,0.90495,0.49005,0.98861,0.5968,1,0.70028,1,0.80652,0.90944,0.97884,0.79068,1,0.70674,1,0.42946,0.81823,0.18337,0.48133,0.1372,0.43598,0.0211,0.39756,0,0.3017,0,0.28153,0.07248,0.36425,0.14778,0.32802,0.22617,0.20733,0.2468,0.09915,0.19812,0.01895,0.13947,0.01745,0.04672,0.11088,0.05541,0.09198,0.14795,0.00748,0.18586,0],"triangles":[20,25,0,24,25,20,21,24,20,24,21,23,1,19,0,20,0,19,22,23,21,18,19,1,15,16,14,13,14,16,12,16,17,13,16,12,11,17,18,12,17,11,5,3,4,2,11,1,10,2,3,11,18,1,2,10,11,9,3,8,6,7,5,9,10,3,8,3,5,7,8,5],"vertices":[1,5,746.79,-170.06,1,1,5,600.12,-148.28,1,1,5,332.03,-213.38,1,1,5,46.04,-225.64,1,1,5,-59.4,-205.61,1,1,5,-109.35,-150.61,1,1,5,-151.86,-88.17,1,1,5,-152.91,59.33,1,1,5,-72.34,132.38,1,1,5,-9.41,175.23,1,1,5,271.21,209.94,1,1,5,590.52,137.56,1,1,5,643.28,134.47,1,1,5,745.69,171.16,1,1,5,799.87,125.59,1,1,5,807.94,113.74,1,1,5,720.5,125.35,1,1,5,678.55,65.63,1,1,5,668.07,-45.33,1,1,5,695.89,-119.43,1,1,5,764.48,-141.72,1,1,5,809.05,-112.66,1,1,5,841.2,-10.41,1,1,5,842.25,-25.95,1,1,5,806.68,-122.85,1,1,5,781.25,-146.6,1],"hull":26}},"titlescreen_cannonB_sideback":{"titlescreen_cannonB_sideback":{"type":"mesh","uvs":[0.98827,0.37312,1,0.67602,1,0.96458,0.83149,1,0.82412,1,0,0.9154,0,0.68811,0.06478,0.22251,0.33434,0,0.54221,0,0.78116,0.02204],"triangles":[1,5,6,7,8,9,9,0,7,0,9,10,0,6,7,1,6,0,1,3,4,4,5,1,2,3,1],"vertices":[1,4,114.68,143.44,1,1,4,119.91,-28.3,1,1,4,119.91,-191.91,1,1,4,44.75,-212,1,1,4,41.47,-212,1,1,4,-326.09,-164.03,1,1,4,-326.09,-35.15,1,1,4,-297.2,228.84,1,1,4,-176.98,355,1,1,4,-84.27,355,1,1,4,22.31,342.51,1],"hull":11}},"titlescreen_cannonB_sidefront":{"titlescreen_cannonB_sidefront":{"type":"mesh","uvs":[0.70404,0,0.976,0.26392,1,0.65827,1,0.96486,0.82891,1,0.81902,1,0,0.91597,0,0.70695,0.04979,0.30143,0.22637,0.06306,0.51816,0],"triangles":[2,6,7,10,0,1,8,9,10,1,8,10,8,1,2,8,2,7,2,5,6,2,4,5,3,4,2],"vertices":[1,4,227.91,422,1,1,4,349.2,272.36,1,1,4,359.91,48.76,1,1,4,359.91,-125.07,1,1,4,283.6,-145,1,1,4,279.19,-145,1,1,4,-86.09,-97.35,1,1,4,-86.09,21.17,1,1,4,-63.88,251.1,1,1,4,14.87,386.25,1,1,4,145.01,422,1],"hull":11}},"titlescreen_deck":{"titlescreen_deck":{"type":"mesh","uvs":[0.92489,0,1,0.51661,1,0.5384,0.92257,0.99883,0.08928,0.99972,0,1,0,0.90637,0.01509,0.42959,0.92054,0],"triangles":[1,8,0,1,3,8,2,3,1,4,7,8,4,6,7,8,3,4,5,6,4],"vertices":[1,1,1027.03,749.14,1,1,1,1199.17,259.39,1,1,1,1199.17,238.74,1,1,1,1021.7,-197.75,1,1,1,-888.21,-198.59,1,1,1,-1092.83,-198.86,1,1,1,-1092.83,-110.1,1,1,1,-1058.24,341.89,1,1,1,1017.05,749.14,1],"hull":9}},"titlescreen_light_ray":{"titlescreen_light_ray":{"type":"mesh","uvs":[0.93607,0,0.97739,0.02811,1,0.07319,1,0.15299,0.98504,0.23242,0.96055,0.36251,0.92028,0.57637,0.85538,0.92103,0.82143,0.92352,0.24421,0.71255,0.19341,0.69976,0.17872,0.81875,0.15914,0.83408,0.13512,0.82658,0.12239,0.80986,0.03276,0.664,0,0.61196,0.00964,0.59108,0.30677,0.36117,0.52271,0.19408,0.62266,0.11674,0.74339,0.02332,0.76947,0.01723,0.8654,0],"triangles":[10,15,17,16,17,15,18,10,17,9,10,18,14,15,10,11,14,10,13,14,11,12,13,11,6,8,9,7,8,6,4,5,23,22,5,20,5,19,20,5,18,19,6,18,5,6,9,18,0,1,2,2,3,0,0,4,23,3,4,0,23,5,22,22,20,21],"vertices":[1,41,57.57,93.47,1,1,41,142.78,15.81,1,1,41,189.4,-108.74,1,1,41,189.4,-329.24,1,1,42,391.08,340.11,1,1,42,747.23,410.18,1,1,42,1332.71,525.37,1,1,43,1927.09,711.01,1,1,43,1956.53,647.12,1,1,43,1795.85,-668.4,1,1,43,1796.78,-778.95,1,1,43,2117.33,-699.82,1,1,43,2170.59,-724.09,1,1,43,2167.23,-777.68,1,1,43,2132.19,-817.61,1,1,43,1811.99,-1124.29,1,1,43,1698.29,-1235.23,1,1,43,1637.27,-1235.35,1,1,42,1185.51,-864.68,1,1,42,603.41,-595.29,1,1,42,334,-470.61,1,1,41,-339.73,29.03,1,1,41,-285.95,45.85,1,1,41,-88.16,93.47,1],"hull":24}},"titlescreen_logo1":{"titlescreen_logo1":{"type":"mesh","uvs":[0.89202,0,0.76761,0.29422,0.63853,0.11024,0.36286,0.13204,0.23554,0.3351,0.11522,0,0,0,0,0.51499,0.23437,1,0.36403,1,0.66423,1,0.79097,1,1,0.51499,1,0,0.74946,0.49966,0.62797,0.21484,0.38793,0.23119,0.25359,0.55826,0.9054,0.10173,0.9679,0.1099,0.97023,0.46968,0.77165,0.87443,0.2349,0.87443,0.05151,0.4983,0.03399,0.15351,0.11225,0.15351],"triangles":[19,18,0,13,19,0,24,6,5,25,24,5,4,25,5,2,16,3,15,16,2,1,0,18,15,2,1,4,3,16,12,20,19,23,24,25,17,23,25,14,15,1,14,1,18,7,6,24,7,24,23,12,19,13,17,4,16,17,25,4,22,23,17,14,20,21,18,20,14,19,20,18,16,15,14,21,16,14,22,17,16,21,22,16,22,7,23,8,7,22,9,22,21,8,22,9,10,9,21,12,11,21,10,21,11,12,21,20],"vertices":[2,49,487.87,305.31,0.74571,53,369.42,310.1,0.25429,2,49,330.25,145.55,0.74571,53,211.8,150.34,0.25429,2,49,166.71,245.45,0.74571,53,48.26,250.24,0.25429,2,49,-182.57,233.61,0.74571,53,-301.02,238.4,0.25429,2,49,-343.89,123.35,0.74571,53,-462.34,128.14,0.25429,2,49,-496.33,305.31,0.74571,53,-614.78,310.1,0.25429,2,49,-642.31,305.31,0.74571,53,-760.76,310.1,0.25429,2,49,-642.31,25.67,0.74571,53,-760.76,30.46,0.25429,2,49,-345.37,-237.69,0.74571,53,-463.82,-232.9,0.25429,2,49,-181.09,-237.69,0.74571,53,-299.54,-232.9,0.25429,2,49,199.27,-237.69,0.74571,53,80.82,-232.9,0.25429,2,49,359.85,-237.69,0.74571,53,241.4,-232.9,0.25429,2,49,624.69,25.67,0.74571,53,506.24,30.46,0.25429,2,49,624.69,305.31,0.74571,53,506.24,310.1,0.25429,2,49,307.25,33.99,0.72857,52,377.43,37.31,0.27143,2,49,153.33,188.65,0.72857,52,223.51,191.97,0.27143,2,49,-150.81,179.77,0.72857,52,-80.63,183.09,0.27143,2,49,-321.01,2.17,0.72857,52,-250.83,5.49,0.27143,2,49,504.83,250.07,0.72857,52,575.01,253.39,0.27143,2,49,584.01,245.63,0.72857,52,654.19,248.95,0.27143,2,49,586.97,50.27,0.72857,52,657.15,53.59,0.27143,2,49,335.37,-169.51,0.72857,52,405.55,-166.19,0.27143,2,49,-344.69,-169.51,0.72857,52,-274.51,-166.19,0.27143,2,49,-577.05,34.73,0.72857,52,-506.87,38.05,0.27143,2,49,-599.25,221.95,0.72857,52,-529.07,225.27,0.27143,2,49,-500.09,221.95,0.72857,52,-429.91,225.27,0.27143],"hull":14}},"titlescreen_pole":{"titlescreen_pole":{"type":"mesh","uvs":[0.65014,0.00213,0.65104,0.00923,0.72009,0.2093,0.72756,0.21524,0.79501,0.23089,0.8204,0.34446,0.77165,0.35496,0.83018,0.52503,0.90284,0.54836,0.92336,0.63971,0.87913,0.66402,0.99531,0.9996,0.8439,0.99907,0.32571,0.99793,0.34973,0.9914,0.00462,0,0.00897,0.00106],"triangles":[6,3,4,6,4,5,9,10,7,9,7,8,3,6,14,1,16,0,2,16,1,15,16,14,14,16,2,14,2,3,6,7,14,7,10,14,12,14,10,13,14,12,12,10,11],"vertices":[1,44,3130.11,-162.83,1,1,44,3106.62,-161.43,1,1,44,2441.88,-147.17,1,1,44,2421.91,-149.92,1,1,44,2366.91,-184.97,1,1,44,1990.25,-168.84,1,1,44,1957.91,-137.56,1,1,44,1392.86,-125.35,1,1,44,1312.26,-161.36,1,1,44,1009.28,-148.43,1,1,44,931.05,-116.02,1,1,44,-183.9,-92.34,1,1,44,-174.87,-4.21,1,1,44,-146.19,297.6,1,1,44,-125.78,281.82,1,1,44,3168.17,212.94,1,1,44,3164.44,210.7,1],"hull":17}},"titlescreen_railings":{"titlescreen_railings":{"type":"mesh","uvs":[0.91466,0,0.99228,0.0762,0.96015,0.1699,0.99999,0.23849,1,0.27913,0.95294,0.32402,0.92883,0.32964,0.9357,0.72653,0.65109,0.80993,0.00489,0.9993,4.7E-4,1,1.9E-4,0.83663,0,0.72378,0.37239,0.61215,0.42886,0.53962,0.44751,0.25172,0.62547,0.10054,0.91287,0,0.64481,0.63608],"triangles":[2,0,1,0,2,17,5,2,3,5,3,4,5,6,2,6,18,16,15,16,18,14,15,18,2,16,17,2,6,16,18,6,7,8,18,7,11,12,13,13,14,18,11,13,18,8,9,11,8,11,18,10,11,9],"vertices":[1,1,962.08,1496.14,1,1,1,1114.07,1397.62,1,1,1,1051.15,1276.45,1,1,1,1129.15,1187.77,1,1,1,1129.17,1135.23,1,1,1,1037.03,1077.19,1,1,1,989.83,1069.92,1,1,1,1003.27,556.74,1,1,1,446.01,448.9,1,1,1,-819.25,204.04,1,1,1,-827.91,203.14,1,1,1,-828.45,414.38,1,1,1,-828.83,560.29,1,1,1,-99.7,704.64,1,1,1,10.88,798.42,1,1,1,47.4,1170.67,1,1,1,395.85,1366.14,1,1,1,958.57,1496.14,1,1,1,433.72,673.69,1],"hull":18}},"titlescreen_ropes":{"titlescreen_ropes":{"type":"mesh","uvs":[0,0.00162,0.05572,8.0E-4,0.11067,0,0.19403,0.13052,0.28224,0.26863,0.31529,0.30822,0.37569,0.36944,0.43495,0.42951,0.53886,0.51233,0.65619,0.58626,0.77037,0.64113,0.99838,0.70582,0.99216,0.72694,0.8169,0.68431,0.75836,0.74574,0.62972,0.83012,0.8102,0.95251,0.79213,0.97756,0.60181,0.84293,0.35526,0.90015,0.4447,1,0.42714,1,0.21611,0.76316,0.15292,0.60553,0.10156,0.47739,0.06842,0.39472,0.05673,0.33026,0.04943,0.28999,0.01857,0.11975,0.11432,0.14245,0.17083,0.28351,0.19611,0.32408,0.23809,0.40125,0.32727,0.5327,0.41016,0.63167,0.51048,0.73633],"triangles":[22,34,35,35,9,10,14,35,10,11,13,10,14,10,13,15,35,14,16,18,15,17,18,16,20,21,19,12,13,11,18,35,15,19,35,18,22,19,21,35,34,9,19,22,35,34,8,9,22,23,34,25,26,31,32,31,5,24,25,32,32,5,6,24,32,33,7,32,6,7,33,32,33,7,8,34,33,8,23,33,34,23,24,33,25,31,32,31,4,5,26,27,30,26,30,31,31,30,4,27,28,29,28,0,1,2,29,1,29,2,3,29,28,1,30,29,3,30,3,4,27,29,30],"vertices":[1,46,-87.21,-441.95,1,1,46,-92.84,-534.23,1,1,46,-98.4,-625.25,1,1,46,-424.29,-737.16,1,1,46,-769.13,-855.57,1,1,46,-869.04,-902.36,1,1,46,-1024.79,-990.06,1,2,46,-1177.63,-1076.12,0.88889,2,-490.89,1554.05,0.11111,2,46,-1391.36,-1231.48,0.66667,2,-318.49,1353.8,0.33333,2,46,-1585.52,-1410.79,0.33333,2,-123.85,1175.02,0.66667,2,46,-1733.29,-1588.67,0.11111,2,65.57,1042.36,0.88889,1,2,443.84,885.93,1,1,2,433.53,834.86,1,1,2,142.76,937.94,1,1,2,45.66,789.39,1,1,2,-167.77,585.37,1,1,2,131.65,289.43,1,1,2,101.68,228.85,1,1,2,-214.07,554.41,1,1,2,-623.1,416.04,1,1,2,-474.7,174.6,1,2,46,-2551.35,-949.9,0.11111,2,-503.85,174.6,0.88889,2,46,-1951.86,-648.02,0.33333,2,-853.95,747.27,0.66667,2,46,-1563.38,-574.86,0.66667,2,-958.77,1128.42,0.33333,2,46,-1247.57,-515.38,0.88889,2,-1043.99,1438.28,0.11111,1,46,-1043.86,-477.01,1,1,46,-886.93,-470.49,1,1,46,-788.88,-466.41,1,1,46,-374.43,-449.19,1,1,46,-442.17,-603,1,1,46,-789.8,-668.42,1,1,46,-891.01,-702.15,1,2,46,-1082.71,-756.24,0.88889,2,-817.48,1622.37,0.11111,2,46,-1411.64,-877.59,0.66667,2,-669.52,1304.52,0.33333,2,46,-1661.41,-994.98,0.33333,2,-532.02,1065.23,0.66667,2,46,-1927.31,-1140.06,0.11111,2,-365.59,812.15,0.88889],"hull":29}},"titlescreen_sail":{"titlescreen_sail":{"type":"mesh","uvs":[0.82063,0,0.82319,0.32218,0.82662,0.43427,0.84625,0.59918,0.897,0.78619,1,0.99459,0.9995,1,0.93293,0.98104,0.76786,0.93493,0.65216,0.90261,0.47077,0.85194,0.34872,0.81785,0.18606,0.77241,0.10024,0.68491,0.02781,0.52835,0,0.36147,0,0.28341,0.02022,5.3E-4,0.19851,5.5E-4,0.52306,5.9E-4,0.77698,6.1E-4,0.83543,0.86465,0.7148,0.65554,0.62518,0.46136,0.57796,0.32559,0.52549,0.12643,0.64578,0.8195,0.46897,0.69702,0.35352,0.54566,0.23403,0.36642,0.21466,0.16925],"triangles":[30,18,19,25,19,20,20,0,1,30,17,18,30,19,25,24,25,20,30,16,17,29,30,25,29,16,30,29,15,16,1,24,20,22,23,2,22,2,3,27,23,22,22,3,4,26,27,22,21,26,22,10,27,26,4,21,22,8,9,26,10,26,9,21,8,26,5,7,4,21,4,7,8,21,7,6,7,5,23,1,2,29,25,24,23,24,1,14,15,29,28,29,24,28,24,23,13,14,29,13,29,28,27,28,23,12,13,28,11,12,28,27,11,28,11,27,10],"vertices":[3,46,-34.68,-862.73,0.19791,48,1249.11,22.36,0.17246,44,3050.11,-672.9,0.62963,3,46,-484.89,-830.07,0.29621,48,798.9,55.02,0.33342,44,2565.36,-628.33,0.37037,3,46,-641.89,-823.07,0.32594,48,641.9,62.02,0.52591,44,2398.83,-610.09,0.14815,3,46,-874.93,-837.92,0.25662,48,408.86,47.18,0.70634,44,2147.3,-600.28,0.03704,2,46,-1143.25,-903.79,0.14979,48,140.55,-18.7,0.85021,2,46,-1448.86,-1057.2,0.06197,48,-165.06,-172.1,0.93803,2,46,-1456.34,-1055.72,0.03164,48,-172.54,-170.63,0.96836,2,46,-1420.41,-943.24,0.05912,48,-136.62,-58.15,0.94088,2,46,-1332.61,-664.27,0.14109,48,-48.81,220.82,0.85891,2,46,-1271.06,-468.74,0.27118,48,12.74,416.36,0.72882,2,46,-1174.57,-162.19,0.42578,48,109.23,722.9,0.57422,2,46,-1109.64,44.08,0.57732,48,174.15,929.17,0.42268,3,46,-1023.11,318.98,0.66657,48,260.68,1204.07,0.29639,44,2084.84,537.77,0.03704,3,46,-888.77,456.71,0.65564,48,395.03,1341.8,0.19621,44,2222.48,667.72,0.14815,3,46,-659.89,563.43,0.51247,48,623.91,1448.52,0.11715,44,2451.8,765.27,0.37037,3,46,-422.92,592.12,0.31227,48,860.87,1477.21,0.0581,44,2686.96,787.7,0.62963,3,46,-313.93,583.13,0.12735,48,969.86,1468.23,0.0208,44,2794.86,776.64,0.85185,3,46,78.17,515.76,0.0325,48,1361.96,1400.85,0.00454,44,3184.21,703.69,0.96296,1,44,3154.15,397.08,1,3,46,6.73,-350.21,0.02232,48,1290.52,534.88,0.01472,44,3099.42,-161.07,0.96296,3,46,-29.35,-787.48,0.0849,48,1254.45,97.61,0.06325,44,3056.61,-597.74,0.85185,2,46,-1244.06,-788.74,0.03642,48,39.73,96.36,0.96358,2,46,-934.97,-605.04,0.29768,48,348.83,280.05,0.70232,2,46,-651.12,-473.05,0.55582,48,632.67,412.04,0.44418,2,46,-454.86,-407.36,0.70392,48,828.94,477.73,0.29608,1,44,2923.54,-148.05,1,2,46,-1154.11,-467.32,0.25332,48,129.68,417.77,0.74668,2,46,-958,-176.92,0.52732,48,325.79,708.17,0.47268,2,46,-730.28,4.49,0.7204,48,553.52,889.58,0.2796,2,46,-463.05,189.64,0.88834,48,820.75,1074.74,0.11166,1,44,2916.29,391.85,1],"hull":21}},"titlescreen_sail_tie":{"titlescreen_sail_tie":{"type":"mesh","uvs":[1,0.52067,1,0.60909,0.88309,1,0.83757,1,0.46782,0.92123,0.69853,0.7014,0.67406,0.57025,0,0.10124,0,0.05135,0.08755,0.0136],"triangles":[7,8,9,6,9,0,7,9,6,6,0,1,5,6,1,2,3,5,4,5,3,1,2,5],"vertices":[1,48,-274.92,-377.77,1,1,48,-298.45,-375.84,1,1,48,-399.81,-334.99,1,1,48,-398.77,-322.42,1,1,48,-369.4,-222.08,1,1,48,-316.15,-290.59,1,1,48,-280.7,-286.71,1,1,48,-140.56,-110.91,1,1,48,-127.29,-112,1,1,48,-119.23,-137,1],"hull":10}},"titlescreen_start":{"titlescreen_start":{"type":"mesh","uvs":[1,0.18076,1,0.64787,0.97689,0.99308,0.04379,0.99095,0,0.65555,0,0.19338,0.04965,0.00847,0.94209,0.00894],"triangles":[7,0,1,4,5,6,3,4,6,2,7,1,3,6,7,2,3,7],"vertices":[2409,-2790.6,2409,-2887.76,2394.11,-2959.56,1793.2,-2959.12,1765,-2889.35,1765,-2793.22,1796.97,-2754.76,2371.71,-2754.86],"hull":8}},"titlescreen_start_push":{"titlescreen_start_push":{"type":"mesh","uvs":[1,0.16948,1,0.6534,0.96404,0.99052,0.04131,0.99286,0,0.64579,0,0.17686,0.05961,0.00856,0.94619,0.00802],"triangles":[4,5,6,7,0,1,2,7,1,3,4,6,2,3,6,2,6,7],"vertices":[2409,-2788.25,2409,-2888.91,2385.84,-2959.03,1791.6,-2959.52,1765,-2887.32,1765,-2789.79,1803.39,-2754.78,2374.35,-2754.67],"hull":8}},"titlescreen_start_shadow":{"titlescreen_start_shadow":{"type":"mesh","uvs":[0.90425,0.07654,0.98841,0.36242,0.96827,0.77813,0.86495,0.9596,0.12846,0.95866,0.02491,0.7465,0.01727,0.37237,0.0672,0.16085,0.13338,0.04116,0.81632,0.04067],"triangles":[4,5,6,0,1,9,8,6,7,8,4,6,1,3,9,2,3,1,4,8,9,3,4,9],"vertices":[2439.51,-2672.37,2512.89,-2797.02,2495.33,-2978.27,2405.23,-3057.38,1763.02,-3056.98,1672.72,-2964.47,1666.06,-2801.35,1709.6,-2709.13,1767.31,-2656.95,2362.83,-2656.73],"hull":10}},"titlescreen_wood":{"titlescreen_wood":{"type":"mesh","uvs":[0.98925,0.77909,1,0.87469,0.98331,1,0.96848,1,0.94684,0.9874,0.00411,0.21408,0.00223,0.25093,0.00255,0.00264,0.04316,0.00743],"triangles":[5,7,8,6,7,5,4,8,0,4,0,1,5,8,4,3,4,1,2,3,1],"vertices":[1,44,1562.17,-1020.68,1,1,44,1510,-1033.38,1,1,44,1445.59,-1001.68,1,1,44,1447.51,-978.39,1,1,44,1457,-944.96,1,1,44,1989.82,501.92,1,1,44,1970.49,506.49,1,1,44,2102.34,495.11,1,1,44,2094.54,431.55,1],"hull":9}}}}],"animations":{"Idle 2":{"slots":{"2":{"attachment":[{},{"time":1.3333,"name":"2"},{"time":1.3667,"name":"3"},{"time":1.4,"name":"4"},{"time":1.4333,"name":"5"},{"time":1.4667,"name":"6"},{"time":1.5,"name":"7"},{"time":1.5333,"name":"8"},{"time":1.5667,"name":"9"},{"time":1.6,"name":"10"},{"time":1.6667,"name":"11"},{"time":1.7,"name":"12"},{"time":1.7333,"name":"13"},{"time":1.7667,"name":"14"},{"time":1.8,"name":"15"},{"time":1.8333}]},"3":{"attachment":[{},{"time":1.3333,"name":"2"},{"time":1.3667,"name":"3"},{"time":1.4,"name":"4"},{"time":1.4333,"name":"5"},{"time":1.4667,"name":"6"},{"time":1.5,"name":"7"},{"time":1.5333,"name":"8"},{"time":1.5667,"name":"9"},{"time":1.6,"name":"10"},{"time":1.6667,"name":"11"},{"time":1.7,"name":"12"},{"time":1.7333,"name":"13"},{"time":1.7667,"name":"14"},{"time":1.8,"name":"15"},{"time":1.8333}]},"croco_eyes_closed":{"attachment":[{},{"time":1.1},{"time":1.1667,"name":"croco_eyes_closed"},{"time":1.2667},{"time":1.3},{"time":1.3667}]},"croco_eyes_half":{"attachment":[{},{"time":1.1,"name":"croco_eyes_half"},{"time":1.1667},{"time":1.2667,"name":"croco_eyes_half"},{"time":1.3667},{"time":2}]},"sword_shine":{"rgba":[{"color":"ffffff00","curve":"stepped"},{"time":0.1667,"color":"ffffff00"},{"time":0.9333,"color":"ffffffff","curve":"stepped"},{"time":1.5,"color":"ffffffff"},{"time":1.8,"color":"ffffff00"}]}},"bones":{"bone37":{"translate":[{"x":41.75,"y":40.09}],"scale":[{"x":1.293,"y":1.293}]},"bone38":{"translate":[{"x":41.75,"y":40.09}],"scale":[{"x":1.293,"y":1.293}],"shear":[{"x":27.59}]},"bone20":{"translate":[{"x":11.73,"y":-22.34,"curve":[0.147,5.57,0.29,0,0.147,-10.61,0.29,0]},{"time":0.4333,"curve":[0.767,0,1.123,60.54,0.767,0,1.123,-74.6]},{"time":1.3333,"x":60.54,"y":-74.6,"curve":[1.453,60.54,1.813,19.9,1.453,-74.6,1.813,-37.9]},{"time":2,"x":11.73,"y":-22.34}]},"bone14":{"rotate":[{"curve":"stepped"},{"time":1,"curve":"stepped"},{"time":2}],"shear":[{"curve":"stepped"},{"time":1,"curve":"stepped"},{"time":2}]},"bone15":{"rotate":[{"value":2.68,"curve":[0.058,2.91,0.112,3.1]},{"time":0.1667,"value":3.1,"curve":[0.444,3.1,0.722,-3.82]},{"time":1,"value":-3.82,"curve":[1.268,-3.82,1.535,12.65]},{"time":1.8,"value":14.68,"curve":[1.867,15.19,1.934,2.4]},{"time":2,"value":2.68}],"shear":[{"x":4.59,"y":5.28,"curve":[0.058,4.84,0.112,5.04,0.058,5.7,0.112,6.03]},{"time":0.1667,"x":5.04,"y":6.03,"curve":[0.444,5.04,0.722,-2.28,0.444,6.03,0.722,-6.26]},{"time":1,"x":-2.28,"y":-6.26,"curve":[1.334,-2.28,1.669,3.08,1.334,-6.26,1.669,2.74]},{"time":2,"x":4.59,"y":5.28}]},"bone16":{"rotate":[{"value":2.68,"curve":[0.084,3.02,0.187,3.1]},{"time":0.2667,"value":3.1,"curve":[0.544,3.1,0.822,-3.82]},{"time":1.1,"value":-3.82,"curve":[1.181,-3.82,1.258,24.95]},{"time":1.3333,"value":25.47,"curve":[1.492,26.54,1.643,53.54]},{"time":1.8,"value":46.59,"curve":[1.866,43.76,1.932,2.39]},{"time":2,"value":2.68}],"shear":[{"x":4.59,"y":5.28,"curve":[0.084,4.95,0.187,5.04,0.084,5.89,0.187,6.03]},{"time":0.2667,"x":5.04,"y":6.03,"curve":[0.544,5.04,0.822,-2.28,0.544,6.03,0.822,-6.26]},{"time":1.1,"x":-2.28,"y":-6.26,"curve":[1.418,-2.28,1.685,3.15,1.418,-6.26,1.685,2.86]},{"time":2,"x":4.59,"y":5.28}]},"bone17":{"rotate":[{"value":2.68,"curve":[0.099,3.08,0.24,3.1]},{"time":0.3333,"value":3.1,"curve":[0.611,3.1,0.991,-3.82]},{"time":1.1667,"value":-3.82,"curve":[1.214,-3.82,1.271,25.16]},{"time":1.3333,"value":25.66,"curve":[1.469,26.74,1.634,44.95]},{"time":1.8,"value":37.96,"curve":[1.867,35.15,1.934,2.4]},{"time":2,"value":2.68}],"shear":[{"x":4.59,"y":5.28,"curve":[0.099,5.02,0.24,5.04,0.099,6,0.24,6.03]},{"time":0.3333,"x":5.04,"y":6.03,"curve":[0.611,5.04,0.991,-2.28,0.611,6.03,0.991,-6.26]},{"time":1.1667,"x":-2.28,"y":-6.26,"curve":[1.36,-2.28,1.696,3.2,1.36,-6.26,1.696,2.95]},{"time":2,"x":4.59,"y":5.28}]},"bone18":{"rotate":[{"value":2.68,"curve":[0.112,3.14,0.294,3.1]},{"time":0.4,"value":3.1,"curve":[0.678,3.1,1.025,-3.82]},{"time":1.2,"value":-3.82,"curve":[1.239,-3.82,1.284,24.6]},{"time":1.3333,"value":24.97,"curve":[1.467,25.99,1.634,36.1]},{"time":1.8,"value":29.35,"curve":[1.868,26.69,1.935,2.4]},{"time":2,"value":2.68}],"shear":[{"x":4.59,"y":5.28,"curve":[0.112,5.07,0.294,5.04,0.112,6.09,0.294,6.03]},{"time":0.4,"x":5.04,"y":6.03,"curve":[0.678,5.04,1.025,-2.28,0.678,6.03,1.025,-6.26]},{"time":1.2,"x":-2.28,"y":-6.26,"curve":[1.386,-2.28,1.709,3.26,1.386,-6.26,1.709,3.05]},{"time":2,"x":4.59,"y":5.28}]},"bone19":{"rotate":[{"value":2.68,"curve":[0.124,3.18,0.349,3.1]},{"time":0.4667,"value":3.1,"curve":[0.744,3.1,1.058,-3.82]},{"time":1.2333,"value":-3.82,"curve":[1.263,-3.82,1.297,32.3]},{"time":1.3333,"value":32.56,"curve":[1.464,33.47,1.632,45.03]},{"time":1.8,"value":36.11,"curve":[1.868,32.59,1.935,2.4]},{"time":2,"value":2.68}],"shear":[{"x":4.59,"y":5.28,"curve":[0.124,5.12,0.349,5.04,0.124,6.18,0.349,6.03]},{"time":0.4667,"x":5.04,"y":6.03,"curve":[0.744,5.04,1.058,-2.28,0.744,6.03,1.058,-6.26]},{"time":1.2333,"x":-2.28,"y":-6.26,"curve":[1.41,-2.28,1.723,3.33,1.41,-6.26,1.723,3.15]},{"time":2,"x":4.59,"y":5.28}]},"bone8":{"rotate":[{"value":1.9,"curve":[0.113,3.44,0.223,4.66]},{"time":0.3333,"value":4.66,"curve":[0.667,4.66,1.056,-5.89]},{"time":1.2667,"value":-5.89,"curve":[1.408,-5.89,1.78,-1.22]},{"time":2,"value":1.9}],"shear":[{"x":0.46,"y":0.66,"curve":[0.113,1.35,0.223,2.06,0.113,1.35,0.223,1.9]},{"time":0.3333,"x":2.06,"y":1.9,"curve":[0.667,2.06,1.056,-4.07,0.667,1.9,1.056,-2.87]},{"time":1.2667,"x":-4.07,"y":-2.87,"curve":[1.408,-4.07,1.78,-1.36,1.408,-2.87,1.78,-0.76]},{"time":2,"x":0.46,"y":0.66}]},"bone7a":{"rotate":[{"value":0.43,"curve":[0.113,0.19,0.223,0]},{"time":0.3333,"curve":[0.667,0,1.056,1.65]},{"time":1.2667,"value":1.65,"curve":[1.3,1.65,1.347,-4.64]},{"time":1.4,"value":-4.71,"curve":[1.441,-4.76,1.486,1.42]},{"time":1.5333,"value":1.34,"curve":[1.692,1.09,1.872,0.72]},{"time":2,"value":0.43}],"translate":[{"curve":[0.057,0,0.436,-5.14,0.057,0,0.436,-15.41]},{"time":0.8667,"x":-5.14,"y":-15.41,"curve":[1.275,-5.14,1.73,0,1.275,-15.41,1.73,0]},{"time":2}],"shear":[{"x":-0.48,"y":-1.29,"curve":[0.113,-0.89,0.223,-1.22,0.113,-1.72,0.223,-2.06]},{"time":0.3333,"x":-1.22,"y":-2.06,"curve":[0.667,-1.22,1.056,1.63,0.667,-2.06,1.056,0.91]},{"time":1.2667,"x":1.63,"y":0.91,"curve":[1.408,1.63,1.78,0.37,1.408,0.91,1.78,-0.4]},{"time":2,"x":-0.48,"y":-1.29}]},"bone7b":{"rotate":[{"curve":[0.144,0,0.289,24.67]},{"time":0.4333,"value":25.03,"curve":[0.622,25.49,0.811,1.65]},{"time":1,"value":1.65,"curve":[1.112,1.65,1.223,1.58]},{"time":1.3333,"value":1.36,"curve":[1.39,1.26,1.445,-2.65]},{"time":1.5,"value":-2.79,"curve":[1.557,-2.92,1.612,0.8]},{"time":1.6667,"value":0.66,"curve":[1.779,0.39,1.89,0]},{"time":2}],"translate":[{"curve":"stepped"},{"time":2}],"shear":[{"x":-1.22,"y":-2.06,"curve":[0.333,-1.22,0.667,1.63,0.333,-2.06,0.667,0.91]},{"time":1,"x":1.63,"y":0.91,"curve":[1.333,1.63,1.667,-1.22,1.333,0.91,1.667,-2.06]},{"time":2,"x":-1.22,"y":-2.06}]},"bone7b2":{"rotate":[{"curve":[0.333,0,0.667,1.65]},{"time":1,"value":1.65,"curve":[1.333,1.65,1.667,0]},{"time":2}],"translate":[{"curve":"stepped"},{"time":2}],"shear":[{"x":-1.22,"y":-2.06,"curve":[0.333,-1.22,0.667,1.63,0.333,-2.06,0.667,0.91]},{"time":1,"x":1.63,"y":0.91,"curve":[1.333,1.63,1.667,-1.22,1.333,0.91,1.667,-2.06]},{"time":2,"x":-1.22,"y":-2.06}]},"bone7b7":{"rotate":[{"value":-2.59,"curve":[0.124,-3.59,0.246,27.87]},{"time":0.3667,"value":27.87,"curve":[0.59,27.87,0.813,-39.41]},{"time":1.0333,"value":-37.64,"curve":[1.147,-36.77,1.197,1.55]},{"time":1.2667,"value":1.55,"curve":[1.401,1.55,1.791,-0.83]},{"time":2,"value":-2.59}],"scale":[{},{"time":0.8333,"x":0.8,"y":0.8},{"time":2}],"shear":[{"x":-0.7,"y":-0.99,"curve":[0.124,-1.69,0.246,-2.5,0.124,-1.98,0.246,-2.81]},{"time":0.3667,"x":-2.5,"y":-2.81,"curve":[0.59,-2.5,0.813,0.1,0.59,-2.81,0.813,-0.18]},{"time":1.0333,"x":1.85,"y":1.58,"curve":[1.147,2.71,1.197,3.39,1.147,2.44,1.197,3.13]},{"time":1.2667,"x":3.39,"y":3.13,"curve":[1.401,3.39,1.791,1.04,1.401,3.13,1.791,0.76]},{"time":2,"x":-0.7,"y":-0.99}]},"bone7b8":{"rotate":[{"value":-1.14,"curve":[0.18,-2.71,0.357,-47.69]},{"time":0.5333,"value":-47.69,"curve":[0.719,-47.69,0.85,-15.62]},{"time":1.0333,"value":-14.14,"curve":[1.184,-12.98,1.307,1.55]},{"time":1.4,"value":1.55,"curve":[1.499,1.55,1.847,0.26]},{"time":2,"value":-1.14}],"shear":[{"x":0.73,"y":0.45,"curve":[0.18,-0.82,0.357,-2.5,0.18,-1.11,0.357,-2.81]},{"time":0.5333,"x":-2.5,"y":-2.81,"curve":[0.719,-2.5,0.85,0.39,0.719,-2.81,0.85,0.11]},{"time":1.0333,"x":1.85,"y":1.58,"curve":[1.184,3,1.307,3.39,1.184,2.73,1.307,3.13]},{"time":1.4,"x":3.39,"y":3.13,"curve":[1.499,3.39,1.847,2.11,1.499,3.13,1.847,1.84]},{"time":2,"x":0.73,"y":0.45}]},"bone7b9":{"rotate":[{"value":-0.01,"curve":[0.224,-1.78,0.446,7.45]},{"time":0.6667,"value":7.45,"curve":[0.816,7.45,0.886,-1.2]},{"time":1.0333,"value":-0.01,"curve":[1.209,1.34,1.359,1.55]},{"time":1.4667,"value":1.55,"curve":[1.538,1.55,1.891,0.89]},{"time":2,"value":-0.01}],"shear":[{"x":1.85,"y":1.58,"curve":[0.224,0.1,0.446,-2.5,0.224,-0.18,0.446,-2.81]},{"time":0.6667,"x":-2.5,"y":-2.81,"curve":[0.816,-2.5,0.886,0.68,0.816,-2.81,0.886,0.4]},{"time":1.0333,"x":1.85,"y":1.58,"curve":[1.209,3.18,1.359,3.39,1.209,2.92,1.359,3.13]},{"time":1.4667,"x":3.39,"y":3.13,"curve":[1.538,3.39,1.891,2.74,1.538,3.13,1.891,2.47]},{"time":2,"x":1.85,"y":1.58}]},"bone7b3":{"rotate":[{"value":4.7,"curve":[0.087,5.46,0.184,5.7]},{"time":0.2667,"value":5.7,"curve":[0.6,5.7,1.023,-3.92]},{"time":1.2333,"value":-3.92,"curve":[1.394,-3.92,1.748,2.38]},{"time":2,"value":4.7}],"scale":[{},{"time":0.9333,"x":1.1,"y":1.1},{"time":2}],"shear":[{"x":2.34,"y":5.33,"curve":[0.087,2.97,0.184,3.18,0.087,5.8,0.184,5.95]},{"time":0.2667,"x":3.18,"y":5.95,"curve":[0.6,3.18,1.023,-4.91,0.6,5.95,1.023,0]},{"time":1.2333,"x":-4.91,"curve":[1.394,-4.91,1.748,0.38,1.394,0,1.748,3.89]},{"time":2,"x":2.34,"y":5.33}]},"bone7b4":{"rotate":[{"value":4.7,"curve":[0.118,5.73,0.288,5.7]},{"time":0.4,"value":5.7,"curve":[0.733,5.7,1.089,-3.92]},{"time":1.3,"value":-3.92,"curve":[1.443,-3.92,1.777,2.64]},{"time":2,"value":4.7}],"shear":[{"x":2.34,"y":5.33,"curve":[0.118,3.2,0.288,3.18,0.118,5.97,0.288,5.95]},{"time":0.4,"x":3.18,"y":5.95,"curve":[0.733,3.18,1.089,-4.91,0.733,5.95,1.089,0]},{"time":1.3,"x":-4.91,"curve":[1.443,-4.91,1.777,0.61,1.443,0,1.777,4.06]},{"time":2,"x":2.34,"y":5.33}]},"bone7b5":{"rotate":[{"value":4.7,"curve":[0.15,6,0.424,5.7]},{"time":0.5667,"value":5.7,"curve":[0.9,5.7,1.189,-3.92]},{"time":1.4,"value":-3.92,"curve":[1.515,-3.92,1.82,3.04]},{"time":2,"value":4.7}],"shear":[{"x":2.34,"y":5.33,"curve":[0.15,3.43,0.424,3.18,0.15,6.13,0.424,5.95]},{"time":0.5667,"x":3.18,"y":5.95,"curve":[0.9,3.18,1.189,-4.91,0.9,5.95,1.189,0]},{"time":1.4,"x":-4.91,"curve":[1.515,-4.91,1.82,0.94,1.515,0,1.82,4.3]},{"time":2,"x":2.34,"y":5.33}]},"bone3":{"rotate":[{"curve":[0.231,0,0.839,3.51]},{"time":1.0333,"value":6.02,"curve":[1.101,6.89,1.033,8.15]},{"time":1.1,"value":8.15},{"time":1.1667,"value":5.57},{"time":1.2,"value":8.15},{"time":1.2333,"value":9.85},{"time":1.2667,"value":8.15},{"time":1.3333,"value":9.79},{"time":1.4,"value":8.15},{"time":1.4333,"value":5.92},{"time":1.4667,"value":8.15,"curve":[1.746,8.15,1.668,0]},{"time":2}],"scale":[{"curve":[0.231,1,0.839,0.986,0.231,1,0.839,1]},{"time":1.0333,"x":0.976,"curve":[1.101,0.973,1.033,0.857,1.101,1,1.033,1]},{"time":1.1,"x":0.857},{"time":1.1667,"x":0.788},{"time":1.2,"x":0.857},{"time":1.2333,"x":0.823},{"time":1.2667,"x":0.857},{"time":1.3333,"x":0.815},{"time":1.4,"x":0.857},{"time":1.4333,"x":0.837},{"time":1.4667,"x":0.857,"curve":[1.746,0.857,1.668,1,1.746,1,1.668,1]},{"time":2}]},"bone4":{"rotate":[{"value":1.32,"curve":[0.129,1.32,0.805,0.52]},{"time":0.9333,"value":-0.6,"curve":[0.945,-0.7,0.956,0.84]},{"time":0.9667,"value":0.74,"curve":[0.989,0.54,1.011,-1.3]},{"time":1.0333,"value":-1.51,"curve":[1.056,-1.72,1.078,-3.99]},{"time":1.1,"value":-4.2,"curve":[1.111,-4.31,1.122,-2.34]},{"time":1.1333,"value":-2.45,"curve":[1.156,-2.65,1.178,-0.44]},{"time":1.2,"value":-0.63,"curve":[1.222,-0.83,1.301,-4.96]},{"time":1.3667,"value":-4.96,"curve":[1.667,-4.96,1.699,1.32]},{"time":2,"value":1.32}],"scale":[{"x":0.948,"curve":[0.129,0.948,0.805,0.757,0.129,1,0.805,1]},{"time":0.9333,"x":0.766},{"time":0.9667,"x":0.755},{"time":1.0333,"x":0.766},{"time":1.1,"x":0.744},{"time":1.1333,"x":0.766},{"time":1.2,"x":0.695},{"time":1.3667,"curve":[1.667,1,1.699,0.948,1.667,1,1.699,1]},{"time":2,"x":0.948}]},"bone33":{"translate":[{"y":-25.13,"curve":[0.154,0,0.316,0,0.154,-12.57,0.316,11.1]},{"time":0.4667,"y":11.1,"curve":[0.811,0,1.156,0,0.811,11.1,1.156,-84.62]},{"time":1.5,"y":-84.62,"curve":[1.671,0,1.832,0,1.671,-84.62,1.832,-39.39]},{"time":2,"y":-25.13}]},"bone28a":{"rotate":[{"value":3.92,"curve":[0.113,3.74,0.223,3.6]},{"time":0.3333,"value":3.6,"curve":[0.667,3.6,1,4.82]},{"time":1.3333,"value":4.82,"curve":[1.557,4.82,1.78,4.28]},{"time":2,"value":3.92}]},"bone28b":{"rotate":[{"value":3.92,"curve":[0.164,3.66,0.408,3.6]},{"time":0.5667,"value":3.6,"curve":[0.9,3.6,1.233,4.82]},{"time":1.5667,"value":4.82,"curve":[1.735,4.82,1.834,4.2]},{"time":2,"value":3.92}]},"bone32":{"rotate":[{"value":3.64,"curve":[0.136,6.57,0.268,9.07]},{"time":0.4,"value":9.07,"curve":[0.612,9.07,0.824,2.91]},{"time":1.0333,"value":-1.64,"curve":[1.158,-4.23,1.224,-6.38]},{"time":1.3,"value":-6.38,"curve":[1.37,-6.38,1.517,-24.01]},{"time":1.6667,"value":-21.73,"curve":[1.788,-19.9,1.912,1.64]},{"time":2,"value":3.64}],"translate":[{"x":-67.81,"y":-50.15,"curve":[0.136,-60.39,0.268,-54.06,0.136,-94.6,0.268,-132.57]},{"time":0.4,"x":-54.06,"y":-132.57,"curve":[0.612,-54.06,0.824,-69.64,0.612,-132.57,0.824,-39.2]},{"time":1.0333,"x":-81.15,"y":29.76,"curve":[1.158,-87.71,1.224,-93.13,1.158,69.12,1.224,101.56]},{"time":1.3,"x":-93.13,"y":101.56,"curve":[1.37,-93.13,1.517,116.92,1.37,101.56,1.517,-552.72]},{"time":1.6667,"x":122.67,"y":-587.18,"curve":[1.788,127.31,1.912,-72.85,1.788,-614.99,1.912,-19.95]},{"time":2,"x":-67.81,"y":-50.15}],"shear":[{"curve":[0.344,0,0.689,15.59,0.344,0,0.689,-13.43]},{"time":1.0333,"x":15.59,"y":-13.43,"curve":[1.356,15.59,1.678,0,1.356,-13.43,1.678,0]},{"time":2}]},"bone":{"translate":[{"y":-23.17,"curve":[0.113,0,0.223,0,0.113,-27.75,0.223,-31.37]},{"time":0.3333,"y":-31.37,"curve":[0.445,0,0.556,0,0.445,-31.37,0.556,-25.35]},{"time":0.6667,"y":-20.31,"curve":[0.734,0,1.168,0,0.734,-17.32,1.168,-10.67]},{"time":1.2667,"y":-6.78,"curve":[1.322,0,1.387,60.72,1.322,-4.58,1.387,-16.96]},{"time":1.4333,"x":60.72,"y":-15.66,"curve":[1.534,60.72,1.634,0,1.534,-12.95,1.634,-0.98]},{"time":1.7333,"y":-4.33,"curve":[1.844,0,1.891,0,1.844,-8.01,1.891,-18.58]},{"time":2,"y":-23.17}]},"bone7b11":{"rotate":[{"curve":[0.322,0,0.644,-285.66]},{"time":0.9667,"value":-285.66,"curve":[1.133,-285.66,1.618,-461.77]},{"time":2,"value":-538.5}],"translate":[{"x":-447.51,"y":50.39,"curve":[0.322,-447.51,0.644,0,0.322,50.39,0.644,0]},{"time":0.9667}],"scale":[{"curve":"stepped"},{"time":0.4667,"curve":[0.633,1,0.8,3.515,0.633,1,0.8,3.515]},{"time":0.9667,"x":3.515,"y":3.515,"curve":[1.311,3.515,1.656,4.781,1.311,3.515,1.656,4.781]},{"time":2,"x":4.781,"y":4.781}]},"bone30":{"rotate":[{"value":1.47,"curve":[0.113,2,0.223,2.39]},{"time":0.3333,"value":2.39,"curve":[0.633,2.39,0.933,-1.81]},{"time":1.2333,"value":-1.81,"curve":[1.49,-1.81,1.747,0.23]},{"time":2,"value":1.47}],"translate":[{"x":-19.61,"y":-11.52,"curve":[0.113,-15.44,0.223,-12.33,0.113,3.4,0.223,14.55]},{"time":0.3333,"x":-12.33,"y":14.55,"curve":[0.633,-12.33,0.933,-45.39,0.633,14.55,0.933,-103.9]},{"time":1.2333,"x":-45.39,"y":-103.9,"curve":[1.49,-45.39,1.747,-29.33,1.49,-103.9,1.747,-46.35]},{"time":2,"x":-19.61,"y":-11.52}]},"bone7":{"translate":[{"x":-26.89,"curve":[0.122,-29.69,0.313,-29.87,0.122,0,0.313,0]},{"time":0.4333,"x":-29.87,"curve":[0.7,-29.87,0.967,0,0.7,0,0.967,0]},{"time":1.2333,"curve":[1.522,0,1.713,-20.17,1.522,0,1.713,0]},{"time":2,"x":-26.89}]},"bone24":{"translate":[{"x":-3.33,"y":2.1,"curve":[0.154,0.61,0.482,0,0.154,-0.38,0.482,0]},{"time":0.6333,"curve":[0.9,0,1.167,-33.39,0.9,0,1.167,21.09]},{"time":1.4333,"x":-33.39,"y":21.09,"curve":[1.678,-33.39,1.757,-9.7,1.678,21.09,1.757,6.12]},{"time":2,"x":-3.33,"y":2.1}]},"bone23":{"translate":[{"x":5.44,"y":-2.45,"curve":[0.079,2.15,0.156,0,0.079,-0.97,0.156,0]},{"time":0.2333,"curve":[0.5,0,0.767,54.47,0.5,0,0.767,-24.6]},{"time":1.0333,"x":54.47,"y":-24.6,"curve":[1.356,54.47,1.679,19.14,1.356,-24.6,1.679,-8.64]},{"time":2,"x":5.44,"y":-2.45}]},"bone22":{"translate":[{"x":10.12,"curve":[0.113,4.3,0.223,0,0.113,0,0.223,0]},{"time":0.3333,"curve":[0.611,0,0.991,50.59,0.611,0,0.991,0]},{"time":1.1667,"x":50.59,"curve":[1.343,50.59,1.724,24.84,1.343,0,1.724,0]},{"time":2,"x":10.12}]},"bone25":{"translate":[{"x":12.81,"y":2.36,"curve":[0.189,0.45,0.582,0,0.189,0.08,0.582,0]},{"time":0.7667,"curve":[1.044,0,1.258,64.07,1.044,0,1.258,11.8]},{"time":1.4333,"x":64.07,"y":11.8,"curve":[1.548,64.07,1.821,24.91,1.548,11.8,1.821,4.59]},{"time":2,"x":12.81,"y":2.36}]},"bone26":{"translate":[{"x":-14.5,"curve":[0.148,-3.55,0.355,0,0.148,0,0.355,0]},{"time":0.5,"curve":[0.778,0,1.091,-72.51,0.778,0,1.091,0]},{"time":1.2667,"x":-72.51,"curve":[1.423,-72.51,1.755,-33.26,1.423,0,1.755,0]},{"time":2,"x":-14.5}]},"bone28":{"translate":[{"curve":[0.333,0,0.667,0,0.333,0,0.667,-31.65]},{"time":1,"y":-31.65,"curve":[1.333,0,1.667,0,1.333,-31.65,1.667,0]},{"time":2}]},"bone35":{"translate":[{"y":4.61,"curve":[0.157,0,0.312,0,0.157,-11.17,0.312,-26.63]},{"time":0.4667,"y":-26.63,"curve":[0.811,0,1.156,0,0.811,-26.63,1.156,39.2]},{"time":1.5,"y":39.2,"curve":[1.668,0,1.835,0,1.668,39.2,1.835,21.7]},{"time":2,"y":4.61}]},"bone6":{"rotate":[{"curve":"stepped"},{"time":1.3667},{"time":1.5333,"value":-4.45},{"time":1.6667,"curve":"stepped"},{"time":2}],"translate":[{"curve":"stepped"},{"time":1.3667},{"time":1.5333,"x":22.66},{"time":1.6667,"curve":"stepped"},{"time":2}],"scale":[{"curve":"stepped"},{"time":1.3667,"curve":"stepped"},{"time":1.6667,"curve":"stepped"},{"time":2}]},"bone13":{"translate":[{"curve":"stepped"},{"time":1,"curve":"stepped"},{"time":1.3333},{"time":1.5,"x":-5.54,"y":21.81},{"time":1.6667}],"scale":[{"curve":"stepped"},{"time":1,"curve":"stepped"},{"time":1.3333},{"time":1.5,"x":0.946,"y":1.045},{"time":1.6667}]},"bone5":{"translate":[{"curve":"stepped"},{"time":1,"curve":"stepped"},{"time":1.2},{"time":1.3333,"x":72.11},{"time":1.5}]},"bone2":{"translate":[{"curve":"stepped"},{"time":1,"curve":"stepped"},{"time":1.2667},{"time":1.4,"x":72.11},{"time":1.5667}]},"Ball 2":{"rotate":[{"value":-21.53,"curve":"stepped"},{"time":1.4,"value":-21.53},{"time":1.5333}],"translate":[{"curve":"stepped"},{"time":1.3333},{"time":1.5333,"x":-1309.38,"y":617.63}],"scale":[{"curve":"stepped"},{"time":1.3333},{"time":1.4,"x":1.164,"y":0.856},{"time":1.4667}]},"Ball 1":{"rotate":[{"curve":"stepped"},{"time":1.3333},{"time":1.4,"value":-29.9}],"translate":[{"x":153.55,"y":-47.46,"curve":"stepped"},{"time":1.3333,"x":153.55,"y":-47.46},{"time":1.4,"x":-237.78,"y":244.03},{"time":1.4667,"x":-668.2,"y":507.61},{"time":1.5333,"x":-1309.38,"y":617.63}],"scale":[{"curve":"stepped"},{"time":1.3333},{"time":1.4,"x":1.251,"y":0.749},{"time":1.4667}]}},"attachments":{"default":{"2":{"2":{"deform":[{"time":1.3333}]},"1":{"deform":[{"curve":"stepped"},{"time":1.3}]},"3":{"deform":[{"time":1.3667}]},"4":{"deform":[{"time":1.4}]},"5":{"deform":[{"time":1.4333}]},"6":{"deform":[{"time":1.4667}]},"7":{"deform":[{"time":1.5}]},"8":{"deform":[{"time":1.5333}]},"9":{"deform":[{"time":1.5667}]},"10":{"deform":[{"time":1.6,"curve":"stepped"},{"time":1.6333}]},"11":{"deform":[{"time":1.6667}]},"12":{"deform":[{"time":1.7}]},"13":{"deform":[{"time":1.7333}]},"14":{"deform":[{"time":1.7667}]},"15":{"deform":[{"time":1.8}]}},"3":{"1":{"deform":[{"curve":"stepped"},{"time":1.3667}]},"2":{"deform":[{"time":1.4}]},"3":{"deform":[{"time":1.4333}]},"4":{"deform":[{"time":1.4667}]},"5":{"deform":[{"time":1.5}]},"6":{"deform":[{"time":1.5333}]},"7":{"deform":[{"time":1.5667}]},"8":{"deform":[{"time":1.6}]},"9":{"deform":[{"time":1.6333}]},"10":{"deform":[{"time":1.6667,"curve":"stepped"},{"time":1.7}]},"11":{"deform":[{"time":1.7333}]},"12":{"deform":[{"time":1.7667}]},"13":{"deform":[{"time":1.8}]},"14":{"deform":[{"time":1.8333}]},"15":{"deform":[{"time":1.8667}]}},"croco_eyes_closed":{"croco_eyes_closed":{"deform":[{"curve":"stepped"},{"time":1.1},{"time":1.2,"vertices":[-5.74939,4.83121,-5.74841,4.83086,0,0,0,0,-9.94226,6.04875,-9.93372,6.04764,-14.86023,13.67279,-14.85645,13.67244,3.6925,9.32899,3.69324,9.32881,3.49255,10.24364,3.49451,10.24339,-2.48645,0.45773,-2.48364,0.45743,-2.17773,20.78085,-2.17444,20.78004,-2.17187,2.12897,-2.17139,2.12869,0,0,-7.35291,12.19962,-7.35254,12.19946]}]}}}}},"Ilde 1":{"slots":{"croco_eyes_closed":{"attachment":[{},{"time":1.1},{"time":1.1667,"name":"croco_eyes_closed"},{"time":1.2667},{"time":1.3667}]},"croco_eyes_half":{"attachment":[{},{"time":1.1,"name":"croco_eyes_half"},{"time":1.1667},{"time":1.2667,"name":"croco_eyes_half"},{"time":1.3667},{"time":2}]},"sword_shine":{"rgba":[{"color":"ffffff00","curve":"stepped"},{"time":0.1667,"color":"ffffff00"},{"time":0.9333,"color":"ffffffff","curve":"stepped"},{"time":1.5,"color":"ffffffff"},{"time":1.8,"color":"ffffff00"}]}},"bones":{"bone20":{"translate":[{"x":11.73,"y":-22.34,"curve":[0.147,5.57,0.29,0,0.147,-10.61,0.29,0]},{"time":0.4333,"curve":[0.767,0,1.1,43.57,0.767,0,1.1,-69.46]},{"time":1.4333,"x":43.57,"y":-69.46,"curve":[1.623,43.57,1.813,19.9,1.623,-69.46,1.813,-37.9]},{"time":2,"x":11.73,"y":-22.34}]},"bone14":{"rotate":[{"curve":"stepped"},{"time":1,"curve":"stepped"},{"time":2}],"shear":[{"curve":"stepped"},{"time":1,"curve":"stepped"},{"time":2}]},"bone15":{"rotate":[{"value":2.68,"curve":[0.058,2.91,0.112,3.1]},{"time":0.1667,"value":3.1,"curve":[0.444,3.1,0.722,-3.82]},{"time":1,"value":-3.82,"curve":[1.334,-3.82,1.669,1.25]},{"time":2,"value":2.68}],"shear":[{"x":4.59,"y":5.28,"curve":[0.058,4.84,0.112,5.04,0.058,5.7,0.112,6.03]},{"time":0.1667,"x":5.04,"y":6.03,"curve":[0.444,5.04,0.722,-2.28,0.444,6.03,0.722,-6.26]},{"time":1,"x":-2.28,"y":-6.26,"curve":[1.334,-2.28,1.669,3.08,1.334,-6.26,1.669,2.74]},{"time":2,"x":4.59,"y":5.28}]},"bone16":{"rotate":[{"value":2.68,"curve":[0.084,3.02,0.187,3.1]},{"time":0.2667,"value":3.1,"curve":[0.544,3.1,0.822,-3.82]},{"time":1.1,"value":-3.82,"curve":[1.418,-3.82,1.685,1.32]},{"time":2,"value":2.68}],"shear":[{"x":4.59,"y":5.28,"curve":[0.084,4.95,0.187,5.04,0.084,5.89,0.187,6.03]},{"time":0.2667,"x":5.04,"y":6.03,"curve":[0.544,5.04,0.822,-2.28,0.544,6.03,0.822,-6.26]},{"time":1.1,"x":-2.28,"y":-6.26,"curve":[1.418,-2.28,1.685,3.15,1.418,-6.26,1.685,2.86]},{"time":2,"x":4.59,"y":5.28}]},"bone17":{"rotate":[{"value":2.68,"curve":[0.099,3.08,0.24,3.1]},{"time":0.3333,"value":3.1,"curve":[0.611,3.1,0.889,-3.82]},{"time":1.1667,"value":-3.82,"curve":[1.473,-3.82,1.696,1.37]},{"time":2,"value":2.68}],"shear":[{"x":4.59,"y":5.28,"curve":[0.099,5.02,0.24,5.04,0.099,6,0.24,6.03]},{"time":0.3333,"x":5.04,"y":6.03,"curve":[0.611,5.04,0.889,-2.28,0.611,6.03,0.889,-6.26]},{"time":1.1667,"x":-2.28,"y":-6.26,"curve":[1.473,-2.28,1.696,3.2,1.473,-6.26,1.696,2.95]},{"time":2,"x":4.59,"y":5.28}]},"bone18":{"rotate":[{"value":2.68,"curve":[0.112,3.14,0.294,3.1]},{"time":0.4,"value":3.1,"curve":[0.678,3.1,0.956,-3.82]},{"time":1.2333,"value":-3.82,"curve":[1.527,-3.82,1.709,1.42]},{"time":2,"value":2.68}],"shear":[{"x":4.59,"y":5.28,"curve":[0.112,5.07,0.294,5.04,0.112,6.09,0.294,6.03]},{"time":0.4,"x":5.04,"y":6.03,"curve":[0.678,5.04,0.956,-2.28,0.678,6.03,0.956,-6.26]},{"time":1.2333,"x":-2.28,"y":-6.26,"curve":[1.527,-2.28,1.709,3.26,1.527,-6.26,1.709,3.05]},{"time":2,"x":4.59,"y":5.28}]},"bone19":{"rotate":[{"value":2.68,"curve":[0.124,3.18,0.349,3.1]},{"time":0.4667,"value":3.1,"curve":[0.744,3.1,1.022,-3.82]},{"time":1.3,"value":-3.82,"curve":[1.58,-3.82,1.723,1.48]},{"time":2,"value":2.68}],"shear":[{"x":4.59,"y":5.28,"curve":[0.124,5.12,0.349,5.04,0.124,6.18,0.349,6.03]},{"time":0.4667,"x":5.04,"y":6.03,"curve":[0.744,5.04,1.022,-2.28,0.744,6.03,1.022,-6.26]},{"time":1.3,"x":-2.28,"y":-6.26,"curve":[1.58,-2.28,1.723,3.33,1.58,-6.26,1.723,3.15]},{"time":2,"x":4.59,"y":5.28}]},"bone8":{"rotate":[{"value":1.9,"curve":[0.113,3.44,0.223,4.66]},{"time":0.3333,"value":4.66,"curve":[0.667,4.66,1,-5.89]},{"time":1.3333,"value":-5.89,"curve":[1.557,-5.89,1.78,-1.22]},{"time":2,"value":1.9}],"shear":[{"x":0.46,"y":0.66,"curve":[0.113,1.35,0.223,2.06,0.113,1.35,0.223,1.9]},{"time":0.3333,"x":2.06,"y":1.9,"curve":[0.667,2.06,1,-4.07,0.667,1.9,1,-2.87]},{"time":1.3333,"x":-4.07,"y":-2.87,"curve":[1.557,-4.07,1.78,-1.36,1.557,-2.87,1.78,-0.76]},{"time":2,"x":0.46,"y":0.66}]},"bone7a":{"rotate":[{"value":0.43,"curve":[0.113,0.19,0.223,0]},{"time":0.3333,"curve":[0.667,0,1,1.65]},{"time":1.3333,"value":1.65,"curve":[1.557,1.65,1.78,0.92]},{"time":2,"value":0.43}],"translate":[{"curve":[0.057,0,0.436,-5.14,0.057,0,0.436,-15.41]},{"time":0.8667,"x":-5.14,"y":-15.41,"curve":[1.275,-5.14,1.73,0,1.275,-15.41,1.73,0]},{"time":2}],"shear":[{"x":-0.48,"y":-1.29,"curve":[0.113,-0.89,0.223,-1.22,0.113,-1.72,0.223,-2.06]},{"time":0.3333,"x":-1.22,"y":-2.06,"curve":[0.667,-1.22,1,1.63,0.667,-2.06,1,0.91]},{"time":1.3333,"x":1.63,"y":0.91,"curve":[1.557,1.63,1.78,0.37,1.557,0.91,1.78,-0.4]},{"time":2,"x":-0.48,"y":-1.29}]},"bone7b":{"rotate":[{"curve":[0.333,0,0.667,1.65]},{"time":1,"value":1.65,"curve":[1.333,1.65,1.667,0]},{"time":2}],"translate":[{"curve":"stepped"},{"time":2}],"shear":[{"x":-1.22,"y":-2.06,"curve":[0.333,-1.22,0.667,1.63,0.333,-2.06,0.667,0.91]},{"time":1,"x":1.63,"y":0.91,"curve":[1.333,1.63,1.667,-1.22,1.333,0.91,1.667,-2.06]},{"time":2,"x":-1.22,"y":-2.06}]},"bone7b2":{"rotate":[{"curve":[0.333,0,0.667,1.65]},{"time":1,"value":1.65,"curve":[1.333,1.65,1.667,0]},{"time":2}],"translate":[{"curve":"stepped"},{"time":2}],"shear":[{"x":-1.22,"y":-2.06,"curve":[0.333,-1.22,0.667,1.63,0.333,-2.06,0.667,0.91]},{"time":1,"x":1.63,"y":0.91,"curve":[1.333,1.63,1.667,-1.22,1.333,0.91,1.667,-2.06]},{"time":2,"x":-1.22,"y":-2.06}]},"bone7b7":{"rotate":[{"value":-2.59,"curve":[0.124,-3.59,0.246,-4.42]},{"time":0.3667,"value":-4.42,"curve":[0.59,-4.42,0.813,-1.78]},{"time":1.0333,"value":-0.01,"curve":[1.147,0.86,1.257,1.55]},{"time":1.3667,"value":1.55,"curve":[1.579,1.55,1.791,-0.83]},{"time":2,"value":-2.59}],"scale":[{},{"time":0.8333,"x":0.8,"y":0.8},{"time":2}],"shear":[{"x":-0.7,"y":-0.99,"curve":[0.124,-1.69,0.246,-2.5,0.124,-1.98,0.246,-2.81]},{"time":0.3667,"x":-2.5,"y":-2.81,"curve":[0.59,-2.5,0.813,0.1,0.59,-2.81,0.813,-0.18]},{"time":1.0333,"x":1.85,"y":1.58,"curve":[1.147,2.71,1.257,3.39,1.147,2.44,1.257,3.13]},{"time":1.3667,"x":3.39,"y":3.13,"curve":[1.579,3.39,1.791,1.04,1.579,3.13,1.791,0.76]},{"time":2,"x":-0.7,"y":-0.99}]},"bone7b8":{"rotate":[{"value":-1.14,"curve":[0.18,-2.71,0.357,-4.42]},{"time":0.5333,"value":-4.42,"curve":[0.719,-4.42,0.85,-1.48]},{"time":1.0333,"value":-0.01,"curve":[1.184,1.15,1.387,1.55]},{"time":1.5333,"value":1.55,"curve":[1.69,1.55,1.847,0.26]},{"time":2,"value":-1.14}],"shear":[{"x":0.73,"y":0.45,"curve":[0.18,-0.82,0.357,-2.5,0.18,-1.11,0.357,-2.81]},{"time":0.5333,"x":-2.5,"y":-2.81,"curve":[0.719,-2.5,0.85,0.39,0.719,-2.81,0.85,0.11]},{"time":1.0333,"x":1.85,"y":1.58,"curve":[1.184,3,1.387,3.39,1.184,2.73,1.387,3.13]},{"time":1.5333,"x":3.39,"y":3.13,"curve":[1.69,3.39,1.847,2.11,1.69,3.13,1.847,1.84]},{"time":2,"x":0.73,"y":0.45}]},"bone7b9":{"rotate":[{"value":-0.01,"curve":[0.224,-1.78,0.446,-4.42]},{"time":0.6667,"value":-4.42,"curve":[0.816,-4.42,0.886,-1.2]},{"time":1.0333,"value":-0.01,"curve":[1.209,1.34,1.496,1.55]},{"time":1.6667,"value":1.55,"curve":[1.779,1.55,1.891,0.89]},{"time":2,"value":-0.01}],"shear":[{"x":1.85,"y":1.58,"curve":[0.224,0.1,0.446,-2.5,0.224,-0.18,0.446,-2.81]},{"time":0.6667,"x":-2.5,"y":-2.81,"curve":[0.816,-2.5,0.886,0.68,0.816,-2.81,0.886,0.4]},{"time":1.0333,"x":1.85,"y":1.58,"curve":[1.209,3.18,1.496,3.39,1.209,2.92,1.496,3.13]},{"time":1.6667,"x":3.39,"y":3.13,"curve":[1.779,3.39,1.891,2.74,1.779,3.13,1.891,2.47]},{"time":2,"x":1.85,"y":1.58}]},"bone7b3":{"rotate":[{"value":4.7,"curve":[0.087,5.46,0.184,5.7]},{"time":0.2667,"value":5.7,"curve":[0.6,5.7,0.933,-3.92]},{"time":1.2667,"value":-3.92,"curve":[1.522,-3.92,1.748,2.38]},{"time":2,"value":4.7}],"scale":[{},{"time":0.9333,"x":1.1,"y":1.1},{"time":2}],"shear":[{"x":2.34,"y":5.33,"curve":[0.087,2.97,0.184,3.18,0.087,5.8,0.184,5.95]},{"time":0.2667,"x":3.18,"y":5.95,"curve":[0.6,3.18,0.933,-4.91,0.6,5.95,0.933,0]},{"time":1.2667,"x":-4.91,"curve":[1.522,-4.91,1.748,0.38,1.522,0,1.748,3.89]},{"time":2,"x":2.34,"y":5.33}]},"bone7b4":{"rotate":[{"value":4.7,"curve":[0.118,5.73,0.288,5.7]},{"time":0.4,"value":5.7,"curve":[0.733,5.7,1.067,-3.92]},{"time":1.4,"value":-3.92,"curve":[1.626,-3.92,1.777,2.64]},{"time":2,"value":4.7}],"shear":[{"x":2.34,"y":5.33,"curve":[0.118,3.2,0.288,3.18,0.118,5.97,0.288,5.95]},{"time":0.4,"x":3.18,"y":5.95,"curve":[0.733,3.18,1.067,-4.91,0.733,5.95,1.067,0]},{"time":1.4,"x":-4.91,"curve":[1.626,-4.91,1.777,0.61,1.626,0,1.777,4.06]},{"time":2,"x":2.34,"y":5.33}]},"bone7b5":{"rotate":[{"value":4.7,"curve":[0.15,6,0.424,5.7]},{"time":0.5667,"value":5.7,"curve":[0.9,5.7,1.233,-3.92]},{"time":1.5667,"value":-3.92,"curve":[1.749,-3.92,1.82,3.04]},{"time":2,"value":4.7}],"shear":[{"x":2.34,"y":5.33,"curve":[0.15,3.43,0.424,3.18,0.15,6.13,0.424,5.95]},{"time":0.5667,"x":3.18,"y":5.95,"curve":[0.9,3.18,1.233,-4.91,0.9,5.95,1.233,0]},{"time":1.5667,"x":-4.91,"curve":[1.749,-4.91,1.82,0.94,1.749,0,1.82,4.3]},{"time":2,"x":2.34,"y":5.33}]},"bone3":{"rotate":[{"curve":[0.333,0,0.667,8.15]},{"time":1,"value":8.15,"curve":[1.333,8.15,1.667,0]},{"time":2}],"scale":[{"curve":[0.333,1,0.667,0.968,0.333,1,0.667,1]},{"time":1,"x":0.968,"curve":[1.333,0.968,1.667,1,1.333,1,1.667,1]},{"time":2}]},"bone4":{"rotate":[{"value":1.32,"curve":[0.333,1.32,0.667,-4.96]},{"time":1,"value":-4.96,"curve":[1.333,-4.96,1.667,1.32]},{"time":2,"value":1.32}],"scale":[{"x":0.948,"curve":[0.333,0.948,0.667,1,0.333,1,0.667,1]},{"time":1,"curve":[1.333,1,1.667,0.948,1.333,1,1.667,1]},{"time":2,"x":0.948}]},"bone33":{"translate":[{"y":-25.13,"curve":[0.154,0,0.316,0,0.154,-12.57,0.316,11.1]},{"time":0.4667,"y":11.1,"curve":[0.811,0,1.156,0,0.811,11.1,1.156,-84.62]},{"time":1.5,"y":-84.62,"curve":[1.671,0,1.832,0,1.671,-84.62,1.832,-39.39]},{"time":2,"y":-25.13}]},"bone28a":{"rotate":[{"value":3.92,"curve":[0.113,3.74,0.223,3.6]},{"time":0.3333,"value":3.6,"curve":[0.667,3.6,1,4.82]},{"time":1.3333,"value":4.82,"curve":[1.557,4.82,1.78,4.28]},{"time":2,"value":3.92}]},"bone28b":{"rotate":[{"value":3.92,"curve":[0.164,3.66,0.408,3.6]},{"time":0.5667,"value":3.6,"curve":[0.9,3.6,1.233,4.82]},{"time":1.5667,"value":4.82,"curve":[1.735,4.82,1.834,4.2]},{"time":2,"value":3.92}]},"bone32":{"rotate":[{"value":3.64,"curve":[0.136,6.57,0.268,9.07]},{"time":0.4,"value":9.07,"curve":[0.612,9.07,0.824,2.91]},{"time":1.0333,"value":-1.64,"curve":[1.158,-4.23,1.279,-6.38]},{"time":1.4,"value":-6.38,"curve":[1.601,-6.38,1.802,-0.83]},{"time":2,"value":3.64}],"translate":[{"x":-67.81,"y":-50.15,"curve":[0.136,-60.39,0.268,-54.06,0.136,-94.6,0.268,-132.57]},{"time":0.4,"x":-54.06,"y":-132.57,"curve":[0.612,-54.06,0.824,-69.64,0.612,-132.57,0.824,-39.2]},{"time":1.0333,"x":-81.15,"y":29.76,"curve":[1.158,-87.71,1.279,-93.13,1.158,69.12,1.279,101.56]},{"time":1.4,"x":-93.13,"y":101.56,"curve":[1.601,-93.13,1.802,-79.09,1.601,101.56,1.802,17.46]},{"time":2,"x":-67.81,"y":-50.15}],"shear":[{"curve":[0.344,0,0.689,15.59,0.344,0,0.689,-13.43]},{"time":1.0333,"x":15.59,"y":-13.43,"curve":[1.356,15.59,1.678,0,1.356,-13.43,1.678,0]},{"time":2}]},"bone":{"translate":[{"y":-23.17,"curve":[0.113,0,0.223,0,0.113,-27.75,0.223,-31.37]},{"time":0.3333,"y":-31.37,"curve":[0.667,0,1,0,0.667,-31.37,1,0]},{"time":1.3333,"curve":[1.557,0,1.78,0,1.557,0,1.78,-13.88]},{"time":2,"y":-23.17}]},"bone7b11":{"rotate":[{"curve":[0.322,0,0.644,-285.66]},{"time":0.9667,"value":-285.66,"curve":[1.133,-285.66,1.618,-461.77]},{"time":2,"value":-538.5}],"translate":[{"x":-447.51,"y":50.39,"curve":[0.322,-447.51,0.644,0,0.322,50.39,0.644,0]},{"time":0.9667}],"scale":[{"curve":"stepped"},{"time":0.4667,"curve":[0.633,1,0.8,3.515,0.633,1,0.8,3.515]},{"time":0.9667,"x":3.515,"y":3.515,"curve":[1.311,3.515,1.656,4.781,1.311,3.515,1.656,4.781]},{"time":2,"x":4.781,"y":4.781}]},"bone30":{"rotate":[{"value":1.47,"curve":[0.113,2,0.223,2.39]},{"time":0.3333,"value":2.39,"curve":[0.633,2.39,0.933,-1.81]},{"time":1.2333,"value":-1.81,"curve":[1.49,-1.81,1.747,0.23]},{"time":2,"value":1.47}],"translate":[{"x":-19.61,"y":-11.52,"curve":[0.113,-15.44,0.223,-12.33,0.113,3.4,0.223,14.55]},{"time":0.3333,"x":-12.33,"y":14.55,"curve":[0.633,-12.33,0.933,-45.39,0.633,14.55,0.933,-103.9]},{"time":1.2333,"x":-45.39,"y":-103.9,"curve":[1.49,-45.39,1.747,-29.33,1.49,-103.9,1.747,-46.35]},{"time":2,"x":-19.61,"y":-11.52}]},"bone7":{"translate":[{"x":-26.89,"curve":[0.122,-29.69,0.313,-29.87,0.122,0,0.313,0]},{"time":0.4333,"x":-29.87,"curve":[0.7,-29.87,0.967,0,0.7,0,0.967,0]},{"time":1.2333,"curve":[1.522,0,1.713,-20.17,1.522,0,1.713,0]},{"time":2,"x":-26.89}]},"bone24":{"translate":[{"x":-3.33,"y":2.1,"curve":[0.154,0.61,0.482,0,0.154,-0.38,0.482,0]},{"time":0.6333,"curve":[0.9,0,1.167,-33.39,0.9,0,1.167,21.09]},{"time":1.4333,"x":-33.39,"y":21.09,"curve":[1.678,-33.39,1.757,-9.7,1.678,21.09,1.757,6.12]},{"time":2,"x":-3.33,"y":2.1}]},"bone23":{"translate":[{"x":5.44,"y":-2.45,"curve":[0.079,2.15,0.156,0,0.079,-0.97,0.156,0]},{"time":0.2333,"curve":[0.5,0,0.767,54.47,0.5,0,0.767,-24.6]},{"time":1.0333,"x":54.47,"y":-24.6,"curve":[1.356,54.47,1.679,19.14,1.356,-24.6,1.679,-8.64]},{"time":2,"x":5.44,"y":-2.45}]},"bone22":{"translate":[{"x":10.12,"curve":[0.113,4.3,0.223,0,0.113,0,0.223,0]},{"time":0.3333,"curve":[0.611,0,0.889,50.59,0.611,0,0.889,0]},{"time":1.1667,"x":50.59,"curve":[1.445,50.59,1.724,24.84,1.445,0,1.724,0]},{"time":2,"x":10.12}]},"bone25":{"translate":[{"x":12.81,"y":2.36,"curve":[0.189,0.45,0.582,0,0.189,0.08,0.582,0]},{"time":0.7667,"curve":[1.044,0,1.322,64.07,1.044,0,1.322,11.8]},{"time":1.6,"x":64.07,"y":11.8,"curve":[1.781,64.07,1.821,24.91,1.781,11.8,1.821,4.59]},{"time":2,"x":12.81,"y":2.36}]},"bone26":{"translate":[{"x":-14.5,"curve":[0.148,-3.55,0.355,0,0.148,0,0.355,0]},{"time":0.5,"curve":[0.778,0,1.056,-72.51,0.778,0,1.056,0]},{"time":1.3333,"x":-72.51,"curve":[1.581,-72.51,1.755,-33.26,1.581,0,1.755,0]},{"time":2,"x":-14.5}]},"bone28":{"translate":[{"curve":[0.333,0,0.667,0,0.333,0,0.667,-31.65]},{"time":1,"y":-31.65,"curve":[1.333,0,1.667,0,1.333,-31.65,1.667,0]},{"time":2}]},"bone35":{"translate":[{"y":4.61,"curve":[0.157,0,0.312,0,0.157,-11.17,0.312,-26.63]},{"time":0.4667,"y":-26.63,"curve":[0.811,0,1.156,0,0.811,-26.63,1.156,39.2]},{"time":1.5,"y":39.2,"curve":[1.668,0,1.835,0,1.668,39.2,1.835,21.7]},{"time":2,"y":4.61}]}}}}}