<autoSpin id="autoSpinOptions" type="tel" max="999999999" textAlign="right" textIndent="1px" background="transparent" border="1px solid #4E4E4E" borderFocus="1px solid #FFF600">
    <layer id="basic" x="512" y="628" pivot="10%,100%">
		<button id="expand" command="expand" x="360" y="22">
			<img id="up" res="@atlas/ui/autospin_btn_expand.png" pivot="50%,50%" tint="0xEEEEEE" />
			<img id="over" res="@atlas/ui/autospin_btn_expand.png" pivot="50%,50%" />
			<img id="disable" res="@atlas/ui/spin_enabled.png" pivot="50%,50%" tint="0x888888" />
		</button>
		<layer id="numSpins">
			<for from="0" to="4" step="1">
				<content>      
					<button id="{%n%}" command="onNumSpins" x="{%x%}" y="{%y%}" >
						<layer id="up">
							<label x="21" y="15" value="{%n%}" fontFamily="Din, Arial" fontSize="18" fill="0xFFFFFF" pivot="50%,50%" />
							<rectangle width="42" height="30" color="0xC89C0C" />
						</layer>
						<layer id="over">
							<label x="21" y="15" value="{%n%}" fontFamily="Din, Arial" fontSize="18" fill="0xFFFFFF" pivot="50%,50%" />
							<rectangle width="42" height="30" color="0xD1BA12" />
						</layer>
						<layer id="disable">
							<label x="21" y="15" value="{%n%}" fontFamily="Din, Arial" fontSize="18" fill="0x1C1B1B" pivot="50%,50%" />
							<rectangle width="42" height="30" color="0xFFF600" />
						</layer>
					</button>
				</content>			
				<arguments>
					<argument id="0" n="100" x="204" y="88" />
					<argument id="1" n="75" x="159" y="88" />
					<argument id="2" n="50" x="114" y="88" />
					<argument id="3" n="25" x="69" y="88" />
					<argument id="4" n="10" x="24" y="88" />
				</arguments>
			</for>
			<button id="-1" command="onNumSpins" x="249" y="88">
				<layer id="up">
					<if name="lang" in="cs,jp,kr">
						<langLabel bitmap="true" x="56" y="7" value="{{unlimited}}" case="upper" align="center" fontFamily="lang" fontSize="18" fill="0xFFFFFF" pivot="0,50%" />
					</if>		
					<if name="lang" in="id">
        				<langLabel bitmap="true" x="56" y="15" value="{{unlimited}}" case="upper" align="center" fontFamily="lang" fontSize="15" fill="0xFFFFFF" pivot="0,50%" />
					</if>
					<if name="lang" in="kh">
						<langLabel bitmap="true" x="56" y="19" value="{{unlimited}}" case="upper" align="center" fontFamily="lang" fontSize="18" fill="0xFFFFFF" pivot="0,50%" />
					</if>		
					<if name="lang" in="vn">
						<langLabel bitmap="true" x="56" y="13" value="{{unlimited}}" case="upper" align="center" fontFamily="lang" fontSize="15" fill="0xFFFFFF" pivot="0,50%" />
					</if>		
					<if name="lang" in="en,th">
						<langLabel bitmap="true" x="56" y="15" value="{{unlimited}}" case="upper" align="center" fontFamily="lang" fontSize="18" fill="0xFFFFFF" pivot="0,50%" />
					</if>
					<rectangle width="116" height="30" color="0xC89C0C" />
				</layer>
				<layer id="over">
					<if name="lang" in="cs,jp,kr">
						<langLabel bitmap="true" x="56" y="7" value="{{unlimited}}" case="upper" align="center" fontFamily="lang" fontSize="18" fill="0xFFFFFF" pivot="0,50%" />
					</if>		
					<if name="lang" in="id">
        				<langLabel bitmap="true" x="56" y="15" value="{{unlimited}}" case="upper" align="center" fontFamily="lang" fontSize="15" fill="0xFFFFFF" pivot="0,50%" />
					</if>
					<if name="lang" in="kh">
						<langLabel bitmap="true" x="56" y="19" value="{{unlimited}}" case="upper" align="center" fontFamily="lang" fontSize="18" fill="0xFFFFFF" pivot="0,50%" />
					</if>		
					<if name="lang" in="vn">
        				<langLabel bitmap="true" x="56" y="13" value="{{unlimited}}" case="upper" align="center" fontFamily="lang" fontSize="15" fill="0xFFFFFF" pivot="0,50%" />
					</if>	
					<if name="lang" in="en,th">
						<langLabel bitmap="true" x="56" y="15" value="{{unlimited}}" case="upper" align="center" fontFamily="lang" fontSize="18" fill="0xFFFFFF" pivot="0,50%" />
					</if>
					<rectangle width="116" height="30" color="0xD1BA12" />
				</layer>
				<layer id="disable">
					<if name="lang" in="cs,jp,kr">
						<langLabel bitmap="true" x="56" y="7" value="{{unlimited}}" case="upper" align="center" fontFamily="lang" fontSize="18" fill="0x1C1B1B" pivot="0,50%" />
					</if>		
					<if name="lang" in="id">
        				<langLabel bitmap="true" x="56" y="15" value="{{unlimited}}" case="upper" align="center" fontFamily="lang" fontSize="15" fill="0x1C1B1B" pivot="0,50%" />
					</if>
					<if name="lang" in="kh">
						<langLabel bitmap="true" x="56" y="19" value="{{unlimited}}" case="upper" align="center" fontFamily="lang" fontSize="18" fill="0x1C1B1B" pivot="0,50%" />
					</if>		
					<if name="lang" in="vn">
        				<langLabel bitmap="true" x="56" y="13" value="{{unlimited}}" case="upper" align="center" fontFamily="lang" fontSize="15" fill="0x1C1B1B" pivot="0,50%" />
					</if>	
					<if name="lang" in="en,th">
						<langLabel bitmap="true" x="56" y="15" value="{{unlimited}}" case="upper" align="center" fontFamily="lang" fontSize="18" fill="0x1C1B1B" pivot="0,50%" />
					</if>
					<rectangle width="116" height="30" color="0xFFF600" />
				</layer>
			</button>
		</layer>
        <langLabel bitmap="true" x="26" y="20" value="{{autospin}}" case="upper" fontFamily="lang" fontSize="24" fill="0xF1C535" />
		<langLabel bitmap="true" x="26" y="62" value="{{numspins}}" case="upper" fontFamily="lang" fontSize="18" fill="0xFFFFFF" />
		<img id="panelBG" res="@atlas/ui/autospin_panel_basic.png" interactive="true" />
    </layer>
    <layer id="advanced" x="512" y="628" visible="false" pivot="10%,100%">
		<button id="collapse" command="collapse" x="360" y="22">
			<img id="up" res="@atlas/ui/autospin_btn_collapse.png" pivot="50%,50%" tint="0xEEEEEE" />
			<img id="over" res="@atlas/ui/autospin_btn_collapse.png" pivot="50%,50%" />
			<img id="disable" res="@atlas/ui/autospin_btn_collapse.png" pivot="50%,50%" tint="0x888888" />
		</button>
		<layer id="numSpins">
			<for from="0" to="4" step="1">
				<content>      
					<button id="{%n%}" command="onNumSpins" x="{%x%}" y="{%y%}" >
						<layer id="up">
							<label x="21" y="15" value="{%n%}" fontFamily="Din, Arial" fontSize="18" fill="0xFFFFFF" pivot="50%,50%" />
							<rectangle width="42" height="30" color="0xC89C0C" />
						</layer>
						<layer id="over">
							<label x="21" y="15" value="{%n%}" fontFamily="Din, Arial" fontSize="18" fill="0xFFFFFF" pivot="50%,50%" />
							<rectangle width="42" height="30" color="0xD1BA12" />
						</layer>
						<layer id="disable">
							<label x="21" y="15" value="{%n%}" fontFamily="Din, Arial" fontSize="18" fill="0x1C1B1B" pivot="50%,50%" />
							<rectangle width="42" height="30" color="0xFFF600" />
						</layer>
					</button>
				</content>			
				<arguments>
					<argument id="0" n="100" x="204" y="88" />
					<argument id="1" n="75" x="159" y="88" />
					<argument id="2" n="50" x="114" y="88" />
					<argument id="3" n="25" x="69" y="88" />
					<argument id="4" n="10" x="24" y="88" />
				</arguments>
			</for>
			<button id="-1" command="onNumSpins" x="249" y="88">
				<layer id="up">
					<if name="lang" in="cs,jp,kr">
						<langLabel bitmap="true" x="56" y="7" value="{{unlimited}}" case="upper" align="center" fontFamily="lang" fontSize="18" fill="0xFFFFFF" pivot="0,50%" />
					</if>		
					<if name="lang" in="id">
        				<langLabel bitmap="true" x="56" y="15" value="{{unlimited}}" case="upper" align="center" fontFamily="lang" fontSize="15" fill="0xFFFFFF" pivot="0,50%" />
					</if>
					<if name="lang" in="kh">
						<langLabel bitmap="true" x="56" y="19" value="{{unlimited}}" case="upper" align="center" fontFamily="lang" fontSize="18" fill="0xFFFFFF" pivot="0,50%" />
					</if>		
					<if name="lang" in="vn">
						<langLabel bitmap="true" x="56" y="13" value="{{unlimited}}" case="upper" align="center" fontFamily="lang" fontSize="15" fill="0xFFFFFF" pivot="0,50%" />
					</if>		
					<if name="lang" in="en,th">
						<langLabel bitmap="true" x="56" y="15" value="{{unlimited}}" case="upper" align="center" fontFamily="lang" fontSize="18" fill="0xFFFFFF" pivot="0,50%" />
					</if>
					<rectangle width="116" height="30" color="0xC89C0C" />
				</layer>
				<layer id="over">
					<if name="lang" in="cs,jp,kr">
						<langLabel bitmap="true" x="56" y="7" value="{{unlimited}}" case="upper" align="center" fontFamily="lang" fontSize="18" fill="0xFFFFFF" pivot="0,50%" />
					</if>		
					<if name="lang" in="id">
        				<langLabel bitmap="true" x="56" y="15" value="{{unlimited}}" case="upper" align="center" fontFamily="lang" fontSize="15" fill="0xFFFFFF" pivot="0,50%" />
					</if>
					<if name="lang" in="kh">
						<langLabel bitmap="true" x="56" y="19" value="{{unlimited}}" case="upper" align="center" fontFamily="lang" fontSize="18" fill="0xFFFFFF" pivot="0,50%" />
					</if>		
					<if name="lang" in="vn">
        				<langLabel bitmap="true" x="56" y="13" value="{{unlimited}}" case="upper" align="center" fontFamily="lang" fontSize="15" fill="0xFFFFFF" pivot="0,50%" />
					</if>	
					<if name="lang" in="en,th">
						<langLabel bitmap="true" x="56" y="15" value="{{unlimited}}" case="upper" align="center" fontFamily="lang" fontSize="18" fill="0xFFFFFF" pivot="0,50%" />
					</if>
					<rectangle width="116" height="30" color="0xD1BA12" />
				</layer>
				<layer id="disable">
					<if name="lang" in="cs,jp,kr">
						<langLabel bitmap="true" x="56" y="7" value="{{unlimited}}" case="upper" align="center" fontFamily="lang" fontSize="18" fill="0x1C1B1B" pivot="0,50%" />
					</if>		
					<if name="lang" in="id">
        				<langLabel bitmap="true" x="56" y="15" value="{{unlimited}}" case="upper" align="center" fontFamily="lang" fontSize="15" fill="0x1C1B1B" pivot="0,50%" />
					</if>
					<if name="lang" in="kh">
						<langLabel bitmap="true" x="56" y="19" value="{{unlimited}}" case="upper" align="center" fontFamily="lang" fontSize="18" fill="0x1C1B1B" pivot="0,50%" />
					</if>		
					<if name="lang" in="vn">
        				<langLabel bitmap="true" x="56" y="13" value="{{unlimited}}" case="upper" align="center" fontFamily="lang" fontSize="15" fill="0x1C1B1B" pivot="0,50%" />
					</if>	
					<if name="lang" in="en,th">
						<langLabel bitmap="true" x="56" y="15" value="{{unlimited}}" case="upper" align="center" fontFamily="lang" fontSize="18" fill="0x1C1B1B" pivot="0,50%" />
					</if>
					<rectangle width="116" height="30" color="0xFFF600" />
				</layer>
			</button>
		</layer>
		<rectangle x="24" y="130" width="341" height="1" color="0xFFFFFF" />
		<layer id="stopLimits">
			<for from="0" to="3" step="1">
				<content>      
					<button id="{%n%}" command="onStopLimit" x="{%x%}" y="{%y%}" >
						<layer id="up">
							<label x="23" y="15" value="{%n%}x" fontFamily="Din, Arial" fontSize="18" fill="0xFFFFFF" pivot="50%,50%" />
							<rectangle width="46" height="30" color="0xC89C0C" />
						</layer>
						<layer id="over">
							<label x="23" y="15" value="{%n%}x" fontFamily="Din, Arial" fontSize="18" fill="0xFFFFFF" pivot="50%,50%" />
							<rectangle width="46" height="30" color="0xD1BA12" />
						</layer>
						<layer id="disable">
							<label x="23" y="15" value="{%n%}x" fontFamily="Din, Arial" fontSize="18" fill="0x1C1B1B" pivot="50%,50%" />
							<rectangle width="46" height="30" color="0xFFF600" />
						</layer>
					</button>
				</content>			
				<arguments>
					<argument id="0" n="5" x="172" y="179" />
					<argument id="1" n="10" x="221" y="179" />
					<argument id="2" n="20" x="270" y="179"/>
					<argument id="3" n="50" x="319" y="179" />
				</arguments>
			</for>
			<button id="-1" command="onStopLimit" x="24" y="245">
				<layer id="up">
					<if name="lang" in="cs,jp,kr">
						<langLabel bitmap="true" x="169" y="7" value="{{nolimit}}" case="upper" align="center" fontFamily="lang" fontSize="18" fill="0xFFFFFF" pivot="0,50%" />
					</if>		
					<if name="lang" in="kh">
						<langLabel bitmap="true" x="169" y="19" value="{{nolimit}}" case="upper" align="center" fontFamily="lang" fontSize="18" fill="0xFFFFFF" pivot="0,50%" />
					</if>		
					<if name="lang" in="vn">
						<langLabel bitmap="true" x="169" y="13" value="{{nolimit}}" case="upper" align="center" fontFamily="lang" fontSize="18" fill="0xFFFFFF" pivot="0,50%" />
					</if>		
					<if name="lang" in="en,id,th">
						<langLabel bitmap="true" x="169" y="15" value="{{nolimit}}" case="upper" align="center" fontFamily="lang" fontSize="18" fill="0xFFFFFF" pivot="0,50%" />
					</if>		
					<rectangle width="341" height="30" color="0xC89C0C" />
				</layer>
				<layer id="over">
					<if name="lang" in="cs,jp,kr">
						<langLabel bitmap="true" x="169" y="7" value="{{nolimit}}" case="upper" align="center" fontFamily="lang" fontSize="18" fill="0xFFFFFF" pivot="0,50%" />
					</if>		
					<if name="lang" in="kh">
						<langLabel bitmap="true" x="169" y="19" value="{{nolimit}}" case="upper" align="center" fontFamily="lang" fontSize="18" fill="0xFFFFFF" pivot="0,50%" />
					</if>		
					<if name="lang" in="vn">
						<langLabel bitmap="true" x="169" y="13" value="{{nolimit}}" case="upper" align="center" fontFamily="lang" fontSize="18" fill="0xFFFFFF" pivot="0,50%" />
					</if>		
					<if name="lang" in="en,id,th">
						<langLabel bitmap="true" x="169" y="15" value="{{nolimit}}" case="upper" align="center" fontFamily="lang" fontSize="18" fill="0xFFFFFF" pivot="0,50%" />
					</if>		
					<rectangle width="341" height="30" color="0xD1BA12" />
				</layer>
				<layer id="disable">
					<if name="lang" in="cs,jp,kr">
						<langLabel bitmap="true" x="169" y="7" value="{{nolimit}}" case="upper" align="center" fontFamily="lang" fontSize="18" fill="0x1C1B1B" pivot="0,50%" />
					</if>		
					<if name="lang" in="kh">
						<langLabel bitmap="true" x="169" y="19" value="{{nolimit}}" case="upper" align="center" fontFamily="lang" fontSize="18" fill="0x1C1B1B" pivot="0,50%" />
					</if>		
					<if name="lang" in="vn">
						<langLabel bitmap="true" x="169" y="13" value="{{nolimit}}" case="upper" align="center" fontFamily="lang" fontSize="18" fill="0x1C1B1B" pivot="0,50%" />
					</if>		
					<if name="lang" in="en,id,th">
						<langLabel bitmap="true" x="169" y="15" value="{{nolimit}}" case="upper" align="center" fontFamily="lang" fontSize="18" fill="0x1C1B1B" pivot="0,50%" />
					</if>
					<rectangle width="341" height="30" color="0xFFF600" />
				</layer>
			</button>
		</layer>
		<label id="customCurrency" x="176" y="227" align="left" fontFamily="Din, Arial" fontSize="15" fill="0x000000" pivot="0,50%"/>
		<label id="winexceedsCurrency" x="226" y="329" align="left" fontFamily="Din, Arial" fontSize="15" fill="0x000000" pivot="0,50%"/>
		<label id="balanceincreassesCurrency" x="226" y="362" align="left" fontFamily="Din, Arial" fontSize="15" fill="0x000000" pivot="0,50%"/>		
		<rectangle id="autospinCustomBox" x="172" y="212" width="193" height="30" color="0xFFFFFF" border="1" borderColor="0x4E4E4E" />
		<rectangle id="autospinWinexceedsBox" x="223" y="314" width="142" height="30" color="0xFFFFFF" border="1" borderColor="0x4E4E4E" />	
		<rectangle id="autospinBalanceincreassesBox" x="223" y="347" width="142" height="30" color="0xFFFFFF" border="1" borderColor="0x4E4E4E" />
		<toggleButton id="byFeatures" x="319" y="382" command="onFeatures">
			<button id="up" pivot="50%,50%">
				<img id="up" res="@atlas/ui/autospin_toggle_off.png" tint="0xEEEEEE" />
				<img id="over" res="@atlas/ui/autospin_toggle_off.png"/>
			</button>
			<button id="down" pivot="50%,50%">
				<img id="up" res="@atlas/ui/autospin_toggle_on.png" tint="0xEEEEEE" />
				<img id="over" res="@atlas/ui/autospin_toggle_on.png" />
			</button>
		</toggleButton>		
		<if name="lang" in="cs,jp,kr">	
			<langLabel bitmap="true" x="26" y="18" value="{{autospin}}" case="upper" fontFamily="lang" fontSize="24" fill="0xF1C535" />
			<langLabel bitmap="true" x="26" y="60" value="{{numspins}}" case="upper" fontFamily="lang" fontSize="18" fill="0xFFFFFF" />
			<langLabel bitmap="true" x="26" y="151" value="{{stoplosslimit}}" case="upper" fontFamily="lang" fontSize="18" fill="0xFFFFFF" />
			<langLabel bitmap="true" x="26" y="290" value="{{stopautospin}}" case="upper" fontFamily="lang" fontSize="18" fill="0xFFFFFF" />
			<langLabel bitmap="true" x="26" y="321" value="{{winexceeds}}" fontFamily="lang" fontSize="18" fill="0xFFFFFF" />	
			<langLabel bitmap="true" x="26" y="354" value="{{balanceincresses}}" fontFamily="lang" fontSize="18" fill="0xFFFFFF" />		
			<langLabel id="labelFeatures" bitmap="true" x="26" y="387" value="{{featureswon}}" fontFamily="lang" fontSize="18" fill="0xFFFFFF" />
		</if>
		<if name="lang" in="cs,jp,kr" not="true">	
			<langLabel bitmap="true" x="26" y="20" value="{{autospin}}" case="upper" fontFamily="lang" fontSize="24" fill="0xF1C535" />
			<langLabel bitmap="true" x="26" y="62" value="{{numspins}}" case="upper" fontFamily="lang" fontSize="18" fill="0xFFFFFF" />
			<langLabel bitmap="true" x="26" y="153" value="{{stoplosslimit}}" case="upper" fontFamily="lang" fontSize="18" fill="0xFFFFFF" />
			<langLabel bitmap="true" x="26" y="294" value="{{stopautospin}}" case="upper" fontFamily="lang" fontSize="18" fill="0xFFFFFF" />	
			<langLabel bitmap="true" x="26" y="356" value="{{balanceincresses}}" fontFamily="lang" fontSize="18" fill="0xFFFFFF" />		
			<langLabel id="labelFeatures" bitmap="true" x="26" y="389" value="{{featureswon}}" fontFamily="lang" fontSize="18" fill="0xFFFFFF" />
		</if>
		<if name="lang" in="id">	
		<langLabel bitmap="true" x="26" y="323" value="{{winexceeds}}" fontFamily="lang" fontSize="14" fill="0xFFFFFF" />
		</if>
		<if name="lang" in="en,kh,th,vn">
		<langLabel bitmap="true" x="26" y="323" value="{{winexceeds}}" fontFamily="lang" fontSize="18" fill="0xFFFFFF" />
		</if>		
		<layer x="24" y="179">
			<if name="lang" in="cs,jp,kr">
			<langLabel bitmap="true" x="71" y="7" value="{{totalbet}}" case="upper" align="center" fontFamily="lang" fontSize="18" fill="0xC2C2C2" pivot="0,50%" />
			</if>		
			<if name="lang" in="kh">
			<langLabel bitmap="true" x="71" y="19" value="{{totalbet}}" case="upper" align="center" fontFamily="lang" fontSize="18" fill="0xC2C2C2" pivot="0,50%" />
			</if>		
			<if name="lang" in="vn">
			<langLabel bitmap="true" x="71" y="13" value="{{totalbet}}" case="upper" align="center" fontFamily="lang" fontSize="18" fill="0xC2C2C2" pivot="0,50%" />
			</if>		
			<if name="lang" in="en,id,th">
			<langLabel bitmap="true" x="71" y="15" value="{{totalbet}}" case="upper" align="center" fontFamily="lang" fontSize="18" fill="0xC2C2C2" pivot="0,50%" />
			</if>		
			<rectangle width="145" height="30" color="0x4E4E4E" />
		</layer>
		<layer x="24" y="212">
			<if name="lang" in="cs,jp,kr">
				<langLabel bitmap="true" x="71" y="7" value="{{custom}}" case="upper" align="center" fontFamily="lang" fontSize="18" fill="0xC2C2C2" pivot="0,50%" />
			</if>
			<if name="lang" in="kh">
				<langLabel bitmap="true" x="71" y="19" value="{{custom}}" case="upper" align="center" fontFamily="lang" fontSize="18" fill="0xC2C2C2" pivot="0,50%" />
			</if>
			<if name="lang" in="vn">
				<langLabel bitmap="true" x="71" y="13" value="{{custom}}" case="upper" align="center" fontFamily="lang" fontSize="18" fill="0xC2C2C2" pivot="0,50%" />
			</if>
			<if name="lang" in="en,id,th">
				<langLabel bitmap="true" x="71" y="15" value="{{custom}}" case="upper" align="center" fontFamily="lang" fontSize="18" fill="0xC2C2C2" pivot="0,50%" />
			</if>
			<rectangle width="145" height="30" color="0x4E4E4E" />
		</layer>		
		<img id="panelBG" res="@atlas/ui/autospin_panel_advanced.png" interactive="true" />
    </layer>
    <rectangle id="clickable" width="1280" height="768" color="0x0" alpha="0" />
</autoSpin>