{"frames": {

"Button_selected.png":
{
	"frame": {"x":1236,"y":778,"w":38,"h":41},
	"rotated": true,
	"trimmed": false,
	"spriteSourceSize": {"x":0,"y":0,"w":38,"h":41},
	"sourceSize": {"w":38,"h":41}
},
"Button_unselected.png":
{
	"frame": {"x":1236,"y":818,"w":31,"h":34},
	"rotated": true,
	"trimmed": false,
	"spriteSourceSize": {"x":0,"y":0,"w":31,"h":34},
	"sourceSize": {"w":31,"h":34}
},
"continue.png":
{
	"frame": {"x":881,"y":853,"w":277,"h":108},
	"rotated": false,
	"trimmed": false,
	"spriteSourceSize": {"x":0,"y":0,"w":277,"h":108},
	"sourceSize": {"w":277,"h":108}
},
"continue_text.png":
{
	"frame": {"x":881,"y":963,"w":259,"h":43},
	"rotated": false,
	"trimmed": false,
	"spriteSourceSize": {"x":0,"y":0,"w":259,"h":43},
	"sourceSize": {"w":259,"h":43}
},
"loading-logo.png":
{
	"frame": {"x":881,"y":1,"w":775,"h":424},
	"rotated": true,
	"trimmed": false,
	"spriteSourceSize": {"x":0,"y":0,"w":775,"h":424},
	"sourceSize": {"w":775,"h":424}
},
"logo.png":
{
	"frame": {"x":881,"y":778,"w":353,"h":73},
	"rotated": false,
	"trimmed": false,
	"spriteSourceSize": {"x":0,"y":0,"w":353,"h":73},
	"sourceSize": {"w":353,"h":73}
},
"Reel.png":
{
	"frame": {"x":1,"y":1,"w":878,"h":975},
	"rotated": false,
	"trimmed": false,
	"spriteSourceSize": {"x":0,"y":0,"w":878,"h":975},
	"sourceSize": {"w":878,"h":975}
}},
"meta": {
	"app": "https://www.codeandweb.com/texturepacker",
	"version": "1.0",
	"image": "en.png",
	"format": "RGBA8888",
	"size": {"w":1306,"h":1007},
	"scale": "1",
	"smartupdate": "$TexturePacker:SmartUpdate:6366f5a40bca57c91fcfabee00bafb0a:d7b58d7511ffcd158cbc2fa13abb91c2:77ed6edc9cdea428c8c272827c6d3d32$"
}
}
