{"frames":{"Button_selected.png":{"frame":{"x":1,"y":1467,"w":38,"h":41},"rotated":false,"trimmed":false,"spriteSourceSize":{"x":0,"y":0,"w":38,"h":41},"sourceSize":{"w":38,"h":41}},"Button_unselected.png":{"frame":{"x":1,"y":1510,"w":31,"h":34},"rotated":false,"trimmed":false,"spriteSourceSize":{"x":0,"y":0,"w":31,"h":34},"sourceSize":{"w":31,"h":34}},"continue.png":{"frame":{"x":598,"y":1438,"w":277,"h":108},"rotated":false,"trimmed":false,"spriteSourceSize":{"x":0,"y":0,"w":277,"h":108},"sourceSize":{"w":277,"h":108}},"continue_text.png":{"frame":{"x":877,"y":1012,"w":122,"h":99},"rotated":true,"trimmed":false,"spriteSourceSize":{"x":0,"y":0,"w":122,"h":99},"sourceSize":{"w":122,"h":99}},"loading-logo.png":{"frame":{"x":48,"y":1012,"w":775,"h":424},"rotated":false,"trimmed":false,"spriteSourceSize":{"x":0,"y":0,"w":775,"h":424},"sourceSize":{"w":775,"h":424}},"logo.png":{"frame":{"x":1,"y":1,"w":984,"h":57},"rotated":false,"trimmed":false,"spriteSourceSize":{"x":0,"y":0,"w":984,"h":57},"sourceSize":{"w":984,"h":57}},"Reel.png":{"frame":{"x":1,"y":60,"w":978,"h":950},"rotated":false,"trimmed":false,"spriteSourceSize":{"x":0,"y":0,"w":978,"h":950},"sourceSize":{"w":978,"h":950}},"text-1.png":{"frame":{"x":877,"y":1136,"w":372,"h":90},"rotated":true,"trimmed":false,"spriteSourceSize":{"x":0,"y":0,"w":372,"h":90},"sourceSize":{"w":372,"h":90}},"text-2.png":{"frame":{"x":48,"y":1438,"w":548,"h":115},"rotated":false,"trimmed":false,"spriteSourceSize":{"x":0,"y":0,"w":548,"h":115},"sourceSize":{"w":548,"h":115}},"text-3.png":{"frame":{"x":1,"y":1012,"w":453,"h":45},"rotated":true,"trimmed":false,"spriteSourceSize":{"x":0,"y":0,"w":453,"h":45},"sourceSize":{"w":453,"h":45}}},"meta":{"app":"https://www.codeandweb.com/texturepacker","version":"1.0","image":"kh.webp","format":"RGBA8888","size":{"w":986,"h":1554},"scale":"1","smartupdate":"$TexturePacker:SmartUpdate:dc329e718acd0503eae6a572239d20f7:22704221699a391bb3499047c23255b9:e52a5c62d91ff8f99f26e7beaa3d4089$"}}