{
	"ការចូលរួមក្នុងហ្គេម GPI": "PARTICIPATING_GAMES", 
	"របៀបលេង?": "1. លេងប្រមូសិនហ្គេម ដោយប្រើ GPI Live Coins (អប្ប. 1) \n2. ប្រម៉ូសិន GPI Live Coins នីមួយៗ អនុញ្ញាតិអោយសមាជិកលេងមួយដៃនៃហ្គេមក្នុងប្រម៉ូសិន។ \n3. លេងនៅក្នុងហ្គេមប្រម៉ូសិន នឹងទទួលបានរង្វាន់។ \n4. ឈ្នះ និងទាមទារង្វាន់នៃប្រម៉ូសិន។",
	"របៀបរក GPI Live Coins?": "1. លេងជាមួយទឹកប្រាក់ពិតជាមួយហ្គេមដែលបានផ្តល់ជូន នៅក្រោមក្លឹប Gameplay Interactive (GPI)។ \n2. Game GPI Live Coins នឹងផ្តល់ជូនដោយចៃដន្យ ក្នុងអំឡុងពេលនៃកម្មវិធី។ \n3. ពិនិត្យមើលរង្វាន់ដែលនៅសល់ ក្នុងអំឡុងពេលនៃកម្មវិធី។ \n4. មានតែសមាជិកដែលសកម្មក្នុងការលេង ក្នុងហ្គេមដែលបានផ្តល់ជូន ដែលនឹងអាចទទួលបាន GPI Live Coins។ \n5. រកបាន GPI Live Coins កាន់តែច្រើន មានឱកាសកាន់តែច្រើនដើម្បីឈ្នះរង្វាន់ពីកម្មវិធី។",
	"របៀបឈ្នះរង្វាន់ក្នុងហ្គេមនៃកម្មវីធី?": "1. ធ្វើតាមការណែនាំ ក្នុងប្រម៉ូសិនហ្គេមនីមួយៗ។ \n2. ដើម្បីឈ្នះរង្វាន់ ដែលបានដាក់ជូនក្នុងប្រម៉ូសិន។ \n3. GPI Live Coins ដែលទទួលបាន តែមិនបានប្រើ ក្នុងអំឡុងពេលនៃកម្មវិធី នឹងត្រូវទុកជាមោឃៈ ឬមិនអាចប្រើប្រាស់បាន។ \n4. រង្វាន់ណាដែលមិនបានទាមទា ក្នុងអំឡុងពេលនៃកម្មវិធីដូចដែលបានដាក់ជូន នឹងត្រូវទុកជាមោឃៈ ឬមិនអាចប្រើប្រាស់បាន។",
	"*ល័ក្ខខ័ណ្ឌត្រូវបានអនុវត្ត*": "[LINK]//info.[%%DOMAIN%%]/share/terms-gpi-games-promotion-participation-km-kh.shtml"
}