{"error_000":"The game encounter connection error.  Please reload or relogin to try again.","error_001":"Request timed out.","youwin":"ANDA MEMENANGKAN","balance":"Saldo","win":"MENANG","totalbet":"Total Taruhan","back":"Kembali","betsetting":"Pengaturan Taruhan","infopage":"Hal. Info","paylines":"Payline","linebet":"Line Bet","payways":"Cara\nMenang","wayswin":"Cara Menang","ways":"Cara","betamount":"Taruhan","betlevel":"Tingkat Taruhan","maxbet":"Maks Taruhan","confirm":"Konfirmasi","soundsetting":"Setting Suara","lines":"Line","line":"Line","autospin":"Spin Otomatis","username":"Username","time":"Waktu","err_000":"The game encounter connection error.  Please reload or relogin to try again.","err_998":"Anda telah bermain selama %time%<br>%winlose%<br>Game ini akan terputus.","err_999":"Anda tidak aktif dalam permainan selama %s% menit. <br>Game ini akan terputus.","closegame":"Silakan tutup atau refresh halaman ini.","instructions":"Untuk melanjutkan, klik continue untuk melanjutkan bermain, atau klik stop untuk hentikan permainan.","msg_spin":"Semoga Beruntung!","msg_nowin":"Game Over! Main Sekarang","msg_linewin":"Line %number%, Menang %win%","msg_scatterwin":"Scatter, Menang %win%","msg_clusterwin":"Cluster win, Pays %win%","msg_bonuswin":"Bonus, Menang %win%","msg_wildwin":"Wild, Menang %win%","msg_featurewin":"Fitur Game, Menang %win%","msg_wayswin":"%number% Way, Menang %win%","msg_lineswin":"%number% Line, Menang %win%","msg_bonus":"Menang Bonus Game!","msg_freespin":"Menang Free Spin!","msg_respin":"Anda memenangkan Respin","ok":"OK","continueplaying":"Continue","stopplaying":"Stop","youvewon":"Kemenangan anda :","youvelost":"Kekalahan anda :","club":"Silahkan transfer dana ke Club Bravado","bet1":"Bet 1","bet2":"Bet 2","bet3":"Bet 3","numspins":"Jumlah Spin","unlimited":"Tak Terbatas","stoplosslimit":"Atur Batas Kekalahan","custom":"Atur","nolimit":"Tanpa Batas","stopautospin":"Hentikan Spin Otomatis","winexceeds":"Saat menang single sejumlah","balanceincresses":"Saat saldo mencapai","featureswon":"Jika menang fitur bonus","startautospin":"Mulai","paytable":"Paytable","sound":"Suara","gamehelp":"Bantuan Game","bethistory":"Sejarah Taruhan","home":"Home","chat":"Obrolan","lobby":"Lobby","settings":"Pengaturan","portraitonly":"Silakan gunakan mode potret untuk pengalaman terbaik","bonuslevel":"Level","bet":"BET","bonus":"BONUS","points":"POIN","cards":"Kartu","gametitle":"Queen Bee"}